package com.stericson.RootTools;

import java.io.IOException;
import java.util.List;
import java.util.concurrent.TimeoutException;

public class Executer
{
  public List<String> sendShell(String[] paramArrayOfString, int paramInt1, IResult paramIResult, boolean paramBoolean, int paramInt2)
    throws IOException, RootToolsException, TimeoutException
  {
    String str1 = InternalVariables.TAG;
    StringBuilder localStringBuilder = new StringBuilder("Sending ").append(paramArrayOfString.length).append(" shell command");
    String str2;
    if (paramArrayOfString.length > 1)
      str2 = "s";
    while (true)
    {
      RootTools.log(str1, str2);
      Worker localWorker = new Worker(paramArrayOfString, paramInt1, paramIResult, paramBoolean, null);
      localWorker.start();
      if (paramInt2 == -1)
        paramInt2 = 300000;
      long l = paramInt2;
      try
      {
        localWorker.join(l);
        Thread.sleep(RootTools.shellDelay);
        if (localWorker.exit != -911)
        {
          List localList = localWorker.finalResponse;
          return localList;
          str2 = "";
        }
        else
        {
          throw new TimeoutException();
        }
      }
      catch (InterruptedException localInterruptedException)
      {
        localWorker.interrupt();
        Thread.currentThread().interrupt();
      }
    }
    throw new TimeoutException();
  }

  private static class Worker extends Thread
  {
    private String[] commands;
    public int exit = -911;
    public List<String> finalResponse;
    private IResult result;
    private int sleepTime;
    private boolean useRoot;

    private Worker(String[] paramArrayOfString, int paramInt, IResult paramIResult, boolean paramBoolean)
    {
      this.commands = paramArrayOfString;
      this.sleepTime = paramInt;
      this.result = paramIResult;
      this.useRoot = paramBoolean;
    }

    // ERROR //
    public void run()
    {
      // Byte code:
      //   0: aconst_null
      //   1: astore_1
      //   2: aconst_null
      //   3: astore_2
      //   4: aconst_null
      //   5: astore_3
      //   6: aconst_null
      //   7: astore 4
      //   9: invokestatic 45	java/lang/Runtime:getRuntime	()Ljava/lang/Runtime;
      //   12: invokevirtual 48	java/lang/Runtime:gc	()V
      //   15: invokestatic 45	java/lang/Runtime:getRuntime	()Ljava/lang/Runtime;
      //   18: astore 17
      //   20: aload_0
      //   21: getfield 31	com/stericson/RootTools/Executer$Worker:useRoot	Z
      //   24: ifeq +283 -> 307
      //   27: ldc 50
      //   29: astore 18
      //   31: aload 17
      //   33: aload 18
      //   35: invokevirtual 54	java/lang/Runtime:exec	(Ljava/lang/String;)Ljava/lang/Process;
      //   38: astore_1
      //   39: aload_0
      //   40: getfield 31	com/stericson/RootTools/Executer$Worker:useRoot	Z
      //   43: ifeq +271 -> 314
      //   46: ldc 56
      //   48: astore 19
      //   50: aload 19
      //   52: invokestatic 62	com/stericson/RootTools/RootTools:log	(Ljava/lang/String;)V
      //   55: aload_0
      //   56: getfield 29	com/stericson/RootTools/Executer$Worker:result	Lcom/stericson/RootTools/IResult;
      //   59: ifnull +14 -> 73
      //   62: aload_0
      //   63: getfield 29	com/stericson/RootTools/Executer$Worker:result	Lcom/stericson/RootTools/IResult;
      //   66: aload_1
      //   67: invokeinterface 68 2 0
      //   72: pop
      //   73: new 70	java/io/DataOutputStream
      //   76: dup
      //   77: aload_1
      //   78: invokevirtual 76	java/lang/Process:getOutputStream	()Ljava/io/OutputStream;
      //   81: invokespecial 79	java/io/DataOutputStream:<init>	(Ljava/io/OutputStream;)V
      //   84: astore 20
      //   86: new 81	java/io/InputStreamReader
      //   89: dup
      //   90: aload_1
      //   91: invokevirtual 85	java/lang/Process:getInputStream	()Ljava/io/InputStream;
      //   94: invokespecial 88	java/io/InputStreamReader:<init>	(Ljava/io/InputStream;)V
      //   97: astore 21
      //   99: new 81	java/io/InputStreamReader
      //   102: dup
      //   103: aload_1
      //   104: invokevirtual 91	java/lang/Process:getErrorStream	()Ljava/io/InputStream;
      //   107: invokespecial 88	java/io/InputStreamReader:<init>	(Ljava/io/InputStream;)V
      //   110: astore 22
      //   112: new 93	java/io/BufferedReader
      //   115: dup
      //   116: aload 21
      //   118: invokespecial 96	java/io/BufferedReader:<init>	(Ljava/io/Reader;)V
      //   121: astore 23
      //   123: new 93	java/io/BufferedReader
      //   126: dup
      //   127: aload 22
      //   129: invokespecial 96	java/io/BufferedReader:<init>	(Ljava/io/Reader;)V
      //   132: astore 24
      //   134: aload_0
      //   135: getfield 29	com/stericson/RootTools/Executer$Worker:result	Lcom/stericson/RootTools/IResult;
      //   138: astore 26
      //   140: aconst_null
      //   141: astore 27
      //   143: aload 26
      //   145: ifnonnull +12 -> 157
      //   148: new 98	java/util/LinkedList
      //   151: dup
      //   152: invokespecial 99	java/util/LinkedList:<init>	()V
      //   155: astore 27
      //   157: aload_0
      //   158: getfield 25	com/stericson/RootTools/Executer$Worker:commands	[Ljava/lang/String;
      //   161: astore 34
      //   163: aload 34
      //   165: arraylength
      //   166: istore 35
      //   168: iconst_0
      //   169: istore 36
      //   171: iload 36
      //   173: iload 35
      //   175: if_icmplt +146 -> 321
      //   178: aload 20
      //   180: ldc 101
      //   182: invokevirtual 104	java/io/DataOutputStream:writeBytes	(Ljava/lang/String;)V
      //   185: aload 20
      //   187: invokevirtual 107	java/io/DataOutputStream:flush	()V
      //   190: aload 23
      //   192: invokevirtual 111	java/io/BufferedReader:readLine	()Ljava/lang/String;
      //   195: astore 37
      //   197: aload 24
      //   199: invokevirtual 111	java/io/BufferedReader:readLine	()Ljava/lang/String;
      //   202: astore 38
      //   204: aload 38
      //   206: astore 39
      //   208: aload 37
      //   210: ifnonnull +182 -> 392
      //   213: aload 39
      //   215: ifnonnull +396 -> 611
      //   218: aload_1
      //   219: ifnull +44 -> 263
      //   222: aload_0
      //   223: aload 27
      //   225: putfield 113	com/stericson/RootTools/Executer$Worker:finalResponse	Ljava/util/List;
      //   228: aload_0
      //   229: aload_1
      //   230: invokevirtual 117	java/lang/Process:waitFor	()I
      //   233: putfield 23	com/stericson/RootTools/Executer$Worker:exit	I
      //   236: aload_0
      //   237: getfield 23	com/stericson/RootTools/Executer$Worker:exit	I
      //   240: putstatic 120	com/stericson/RootTools/RootTools:lastExitCode	I
      //   243: aload_0
      //   244: getfield 29	com/stericson/RootTools/Executer$Worker:result	Lcom/stericson/RootTools/IResult;
      //   247: ifnull +676 -> 923
      //   250: aload_0
      //   251: getfield 29	com/stericson/RootTools/Executer$Worker:result	Lcom/stericson/RootTools/IResult;
      //   254: aload_0
      //   255: getfield 23	com/stericson/RootTools/Executer$Worker:exit	I
      //   258: invokeinterface 124 2 0
      //   263: aload_1
      //   264: ifnull +7 -> 271
      //   267: aload_1
      //   268: invokevirtual 127	java/lang/Process:destroy	()V
      //   271: aload 20
      //   273: ifnull +13 -> 286
      //   276: aload 20
      //   278: invokevirtual 107	java/io/DataOutputStream:flush	()V
      //   281: aload 20
      //   283: invokevirtual 130	java/io/DataOutputStream:close	()V
      //   286: aload 21
      //   288: ifnull +8 -> 296
      //   291: aload 21
      //   293: invokevirtual 131	java/io/InputStreamReader:close	()V
      //   296: aload 22
      //   298: ifnull +708 -> 1006
      //   301: aload 22
      //   303: invokevirtual 131	java/io/InputStreamReader:close	()V
      //   306: return
      //   307: ldc 133
      //   309: astore 18
      //   311: goto -280 -> 31
      //   314: ldc 135
      //   316: astore 19
      //   318: goto -268 -> 50
      //   321: aload 34
      //   323: iload 36
      //   325: aaload
      //   326: astore 43
      //   328: new 137	java/lang/StringBuilder
      //   331: dup
      //   332: ldc 139
      //   334: invokespecial 141	java/lang/StringBuilder:<init>	(Ljava/lang/String;)V
      //   337: aload 43
      //   339: invokevirtual 145	java/lang/StringBuilder:append	(Ljava/lang/String;)Ljava/lang/StringBuilder;
      //   342: invokevirtual 148	java/lang/StringBuilder:toString	()Ljava/lang/String;
      //   345: invokestatic 62	com/stericson/RootTools/RootTools:log	(Ljava/lang/String;)V
      //   348: aload 20
      //   350: new 137	java/lang/StringBuilder
      //   353: dup
      //   354: aload 43
      //   356: invokestatic 154	java/lang/String:valueOf	(Ljava/lang/Object;)Ljava/lang/String;
      //   359: invokespecial 141	java/lang/StringBuilder:<init>	(Ljava/lang/String;)V
      //   362: ldc 156
      //   364: invokevirtual 145	java/lang/StringBuilder:append	(Ljava/lang/String;)Ljava/lang/StringBuilder;
      //   367: invokevirtual 148	java/lang/StringBuilder:toString	()Ljava/lang/String;
      //   370: invokevirtual 104	java/io/DataOutputStream:writeBytes	(Ljava/lang/String;)V
      //   373: aload 20
      //   375: invokevirtual 107	java/io/DataOutputStream:flush	()V
      //   378: aload_0
      //   379: getfield 27	com/stericson/RootTools/Executer$Worker:sleepTime	I
      //   382: i2l
      //   383: invokestatic 160	java/lang/Thread:sleep	(J)V
      //   386: iinc 36 1
      //   389: goto -218 -> 171
      //   392: aload_0
      //   393: getfield 29	com/stericson/RootTools/Executer$Worker:result	Lcom/stericson/RootTools/IResult;
      //   396: ifnonnull +43 -> 439
      //   399: aload 27
      //   401: aload 37
      //   403: invokeinterface 166 2 0
      //   408: pop
      //   409: new 137	java/lang/StringBuilder
      //   412: dup
      //   413: ldc 168
      //   415: invokespecial 141	java/lang/StringBuilder:<init>	(Ljava/lang/String;)V
      //   418: aload 37
      //   420: invokevirtual 145	java/lang/StringBuilder:append	(Ljava/lang/String;)Ljava/lang/StringBuilder;
      //   423: invokevirtual 148	java/lang/StringBuilder:toString	()Ljava/lang/String;
      //   426: invokestatic 62	com/stericson/RootTools/RootTools:log	(Ljava/lang/String;)V
      //   429: aload 23
      //   431: invokevirtual 111	java/io/BufferedReader:readLine	()Ljava/lang/String;
      //   434: astore 37
      //   436: goto -228 -> 208
      //   439: aload_0
      //   440: getfield 29	com/stericson/RootTools/Executer$Worker:result	Lcom/stericson/RootTools/IResult;
      //   443: aload 37
      //   445: invokeinterface 171 2 0
      //   450: goto -41 -> 409
      //   453: astore 30
      //   455: aload_0
      //   456: getfield 29	com/stericson/RootTools/Executer$Worker:result	Lcom/stericson/RootTools/IResult;
      //   459: ifnull +14 -> 473
      //   462: aload_0
      //   463: getfield 29	com/stericson/RootTools/Executer$Worker:result	Lcom/stericson/RootTools/IResult;
      //   466: aload 30
      //   468: invokeinterface 175 2 0
      //   473: aload_1
      //   474: ifnull -211 -> 263
      //   477: aload_0
      //   478: aload 27
      //   480: putfield 113	com/stericson/RootTools/Executer$Worker:finalResponse	Ljava/util/List;
      //   483: aload_0
      //   484: aload_1
      //   485: invokevirtual 117	java/lang/Process:waitFor	()I
      //   488: putfield 23	com/stericson/RootTools/Executer$Worker:exit	I
      //   491: aload_0
      //   492: getfield 23	com/stericson/RootTools/Executer$Worker:exit	I
      //   495: putstatic 120	com/stericson/RootTools/RootTools:lastExitCode	I
      //   498: aload_0
      //   499: getfield 29	com/stericson/RootTools/Executer$Worker:result	Lcom/stericson/RootTools/IResult;
      //   502: ifnull +332 -> 834
      //   505: aload_0
      //   506: getfield 29	com/stericson/RootTools/Executer$Worker:result	Lcom/stericson/RootTools/IResult;
      //   509: aload_0
      //   510: getfield 23	com/stericson/RootTools/Executer$Worker:exit	I
      //   513: invokeinterface 124 2 0
      //   518: goto -255 -> 263
      //   521: astore 25
      //   523: aload 22
      //   525: astore 7
      //   527: aload 21
      //   529: astore 8
      //   531: aload 20
      //   533: astore 6
      //   535: aload_1
      //   536: ifnull +7 -> 543
      //   539: aload_1
      //   540: invokevirtual 127	java/lang/Process:destroy	()V
      //   543: aload 6
      //   545: ifnull +13 -> 558
      //   548: aload 6
      //   550: invokevirtual 107	java/io/DataOutputStream:flush	()V
      //   553: aload 6
      //   555: invokevirtual 130	java/io/DataOutputStream:close	()V
      //   558: aload 8
      //   560: ifnull +8 -> 568
      //   563: aload 8
      //   565: invokevirtual 131	java/io/InputStreamReader:close	()V
      //   568: aload 7
      //   570: ifnull -264 -> 306
      //   573: aload 7
      //   575: invokevirtual 131	java/io/InputStreamReader:close	()V
      //   578: return
      //   579: astore 9
      //   581: getstatic 178	com/stericson/RootTools/RootTools:debugMode	Z
      //   584: ifeq -278 -> 306
      //   587: new 137	java/lang/StringBuilder
      //   590: dup
      //   591: ldc 180
      //   593: invokespecial 141	java/lang/StringBuilder:<init>	(Ljava/lang/String;)V
      //   596: aload 9
      //   598: invokevirtual 183	java/lang/Exception:getMessage	()Ljava/lang/String;
      //   601: invokevirtual 145	java/lang/StringBuilder:append	(Ljava/lang/String;)Ljava/lang/StringBuilder;
      //   604: invokevirtual 148	java/lang/StringBuilder:toString	()Ljava/lang/String;
      //   607: invokestatic 62	com/stericson/RootTools/RootTools:log	(Ljava/lang/String;)V
      //   610: return
      //   611: aload_0
      //   612: getfield 29	com/stericson/RootTools/Executer$Worker:result	Lcom/stericson/RootTools/IResult;
      //   615: ifnonnull +43 -> 658
      //   618: aload 27
      //   620: aload 39
      //   622: invokeinterface 166 2 0
      //   627: pop
      //   628: new 137	java/lang/StringBuilder
      //   631: dup
      //   632: ldc 185
      //   634: invokespecial 141	java/lang/StringBuilder:<init>	(Ljava/lang/String;)V
      //   637: aload 39
      //   639: invokevirtual 145	java/lang/StringBuilder:append	(Ljava/lang/String;)Ljava/lang/StringBuilder;
      //   642: invokevirtual 148	java/lang/StringBuilder:toString	()Ljava/lang/String;
      //   645: invokestatic 62	com/stericson/RootTools/RootTools:log	(Ljava/lang/String;)V
      //   648: aload 24
      //   650: invokevirtual 111	java/io/BufferedReader:readLine	()Ljava/lang/String;
      //   653: astore 39
      //   655: goto -442 -> 213
      //   658: aload_0
      //   659: getfield 29	com/stericson/RootTools/Executer$Worker:result	Lcom/stericson/RootTools/IResult;
      //   662: aload 39
      //   664: invokeinterface 188 2 0
      //   669: goto -41 -> 628
      //   672: astore 28
      //   674: aload_1
      //   675: ifnull +44 -> 719
      //   678: aload_0
      //   679: aload 27
      //   681: putfield 113	com/stericson/RootTools/Executer$Worker:finalResponse	Ljava/util/List;
      //   684: aload_0
      //   685: aload_1
      //   686: invokevirtual 117	java/lang/Process:waitFor	()I
      //   689: putfield 23	com/stericson/RootTools/Executer$Worker:exit	I
      //   692: aload_0
      //   693: getfield 23	com/stericson/RootTools/Executer$Worker:exit	I
      //   696: putstatic 120	com/stericson/RootTools/RootTools:lastExitCode	I
      //   699: aload_0
      //   700: getfield 29	com/stericson/RootTools/Executer$Worker:result	Lcom/stericson/RootTools/IResult;
      //   703: ifnull +202 -> 905
      //   706: aload_0
      //   707: getfield 29	com/stericson/RootTools/Executer$Worker:result	Lcom/stericson/RootTools/IResult;
      //   710: aload_0
      //   711: getfield 23	com/stericson/RootTools/Executer$Worker:exit	I
      //   714: invokeinterface 124 2 0
      //   719: aload 28
      //   721: athrow
      //   722: astore 11
      //   724: aload 22
      //   726: astore 4
      //   728: aload 21
      //   730: astore_3
      //   731: aload 20
      //   733: astore_2
      //   734: getstatic 178	com/stericson/RootTools/RootTools:debugMode	Z
      //   737: ifeq +26 -> 763
      //   740: new 137	java/lang/StringBuilder
      //   743: dup
      //   744: ldc 180
      //   746: invokespecial 141	java/lang/StringBuilder:<init>	(Ljava/lang/String;)V
      //   749: aload 11
      //   751: invokevirtual 183	java/lang/Exception:getMessage	()Ljava/lang/String;
      //   754: invokevirtual 145	java/lang/StringBuilder:append	(Ljava/lang/String;)Ljava/lang/StringBuilder;
      //   757: invokevirtual 148	java/lang/StringBuilder:toString	()Ljava/lang/String;
      //   760: invokestatic 62	com/stericson/RootTools/RootTools:log	(Ljava/lang/String;)V
      //   763: aload_1
      //   764: ifnull +7 -> 771
      //   767: aload_1
      //   768: invokevirtual 127	java/lang/Process:destroy	()V
      //   771: aload_2
      //   772: ifnull +11 -> 783
      //   775: aload_2
      //   776: invokevirtual 107	java/io/DataOutputStream:flush	()V
      //   779: aload_2
      //   780: invokevirtual 130	java/io/DataOutputStream:close	()V
      //   783: aload_3
      //   784: ifnull +7 -> 791
      //   787: aload_3
      //   788: invokevirtual 131	java/io/InputStreamReader:close	()V
      //   791: aload 4
      //   793: ifnull -487 -> 306
      //   796: aload 4
      //   798: invokevirtual 131	java/io/InputStreamReader:close	()V
      //   801: return
      //   802: astore 15
      //   804: getstatic 178	com/stericson/RootTools/RootTools:debugMode	Z
      //   807: ifeq -501 -> 306
      //   810: new 137	java/lang/StringBuilder
      //   813: dup
      //   814: ldc 180
      //   816: invokespecial 141	java/lang/StringBuilder:<init>	(Ljava/lang/String;)V
      //   819: aload 15
      //   821: invokevirtual 183	java/lang/Exception:getMessage	()Ljava/lang/String;
      //   824: invokevirtual 145	java/lang/StringBuilder:append	(Ljava/lang/String;)Ljava/lang/StringBuilder;
      //   827: invokevirtual 148	java/lang/StringBuilder:toString	()Ljava/lang/String;
      //   830: invokestatic 62	com/stericson/RootTools/RootTools:log	(Ljava/lang/String;)V
      //   833: return
      //   834: aload 27
      //   836: aload_0
      //   837: getfield 23	com/stericson/RootTools/Executer$Worker:exit	I
      //   840: invokestatic 193	java/lang/Integer:toString	(I)Ljava/lang/String;
      //   843: invokeinterface 166 2 0
      //   848: pop
      //   849: goto -586 -> 263
      //   852: astore 12
      //   854: aload 22
      //   856: astore 4
      //   858: aload 21
      //   860: astore_3
      //   861: aload 20
      //   863: astore_2
      //   864: aload_1
      //   865: ifnull +7 -> 872
      //   868: aload_1
      //   869: invokevirtual 127	java/lang/Process:destroy	()V
      //   872: aload_2
      //   873: ifnull +11 -> 884
      //   876: aload_2
      //   877: invokevirtual 107	java/io/DataOutputStream:flush	()V
      //   880: aload_2
      //   881: invokevirtual 130	java/io/DataOutputStream:close	()V
      //   884: aload_3
      //   885: ifnull +7 -> 892
      //   888: aload_3
      //   889: invokevirtual 131	java/io/InputStreamReader:close	()V
      //   892: aload 4
      //   894: ifnull +8 -> 902
      //   897: aload 4
      //   899: invokevirtual 131	java/io/InputStreamReader:close	()V
      //   902: aload 12
      //   904: athrow
      //   905: aload 27
      //   907: aload_0
      //   908: getfield 23	com/stericson/RootTools/Executer$Worker:exit	I
      //   911: invokestatic 193	java/lang/Integer:toString	(I)Ljava/lang/String;
      //   914: invokeinterface 166 2 0
      //   919: pop
      //   920: goto -201 -> 719
      //   923: aload 27
      //   925: aload_0
      //   926: getfield 23	com/stericson/RootTools/Executer$Worker:exit	I
      //   929: invokestatic 193	java/lang/Integer:toString	(I)Ljava/lang/String;
      //   932: invokeinterface 166 2 0
      //   937: pop
      //   938: goto -675 -> 263
      //   941: astore 13
      //   943: getstatic 178	com/stericson/RootTools/RootTools:debugMode	Z
      //   946: ifeq -44 -> 902
      //   949: new 137	java/lang/StringBuilder
      //   952: dup
      //   953: ldc 180
      //   955: invokespecial 141	java/lang/StringBuilder:<init>	(Ljava/lang/String;)V
      //   958: aload 13
      //   960: invokevirtual 183	java/lang/Exception:getMessage	()Ljava/lang/String;
      //   963: invokevirtual 145	java/lang/StringBuilder:append	(Ljava/lang/String;)Ljava/lang/StringBuilder;
      //   966: invokevirtual 148	java/lang/StringBuilder:toString	()Ljava/lang/String;
      //   969: invokestatic 62	com/stericson/RootTools/RootTools:log	(Ljava/lang/String;)V
      //   972: goto -70 -> 902
      //   975: astore 32
      //   977: getstatic 178	com/stericson/RootTools/RootTools:debugMode	Z
      //   980: ifeq +26 -> 1006
      //   983: new 137	java/lang/StringBuilder
      //   986: dup
      //   987: ldc 180
      //   989: invokespecial 141	java/lang/StringBuilder:<init>	(Ljava/lang/String;)V
      //   992: aload 32
      //   994: invokevirtual 183	java/lang/Exception:getMessage	()Ljava/lang/String;
      //   997: invokevirtual 145	java/lang/StringBuilder:append	(Ljava/lang/String;)Ljava/lang/StringBuilder;
      //   1000: invokevirtual 148	java/lang/StringBuilder:toString	()Ljava/lang/String;
      //   1003: invokestatic 62	com/stericson/RootTools/RootTools:log	(Ljava/lang/String;)V
      //   1006: return
      //   1007: astore 10
      //   1009: goto -466 -> 543
      //   1012: astore 16
      //   1014: goto -243 -> 771
      //   1017: astore 14
      //   1019: goto -147 -> 872
      //   1022: astore 33
      //   1024: goto -753 -> 271
      //   1027: astore 12
      //   1029: goto -165 -> 864
      //   1032: astore 12
      //   1034: aload 20
      //   1036: astore_2
      //   1037: aconst_null
      //   1038: astore 4
      //   1040: aconst_null
      //   1041: astore_3
      //   1042: goto -178 -> 864
      //   1045: astore 12
      //   1047: aload 21
      //   1049: astore_3
      //   1050: aload 20
      //   1052: astore_2
      //   1053: aconst_null
      //   1054: astore 4
      //   1056: goto -192 -> 864
      //   1059: astore 11
      //   1061: aconst_null
      //   1062: astore_2
      //   1063: aconst_null
      //   1064: astore 4
      //   1066: aconst_null
      //   1067: astore_3
      //   1068: goto -334 -> 734
      //   1071: astore 11
      //   1073: aload 20
      //   1075: astore_2
      //   1076: aconst_null
      //   1077: astore 4
      //   1079: aconst_null
      //   1080: astore_3
      //   1081: goto -347 -> 734
      //   1084: astore 11
      //   1086: aload 21
      //   1088: astore_3
      //   1089: aload 20
      //   1091: astore_2
      //   1092: aconst_null
      //   1093: astore 4
      //   1095: goto -361 -> 734
      //   1098: astore 5
      //   1100: aconst_null
      //   1101: astore 6
      //   1103: aconst_null
      //   1104: astore 7
      //   1106: aconst_null
      //   1107: astore 8
      //   1109: goto -574 -> 535
      //   1112: astore 45
      //   1114: aload 20
      //   1116: astore 6
      //   1118: aconst_null
      //   1119: astore 7
      //   1121: aconst_null
      //   1122: astore 8
      //   1124: goto -589 -> 535
      //   1127: astore 44
      //   1129: aload 21
      //   1131: astore 8
      //   1133: aload 20
      //   1135: astore 6
      //   1137: aconst_null
      //   1138: astore 7
      //   1140: goto -605 -> 535
      //
      // Exception table:
      //   from	to	target	type
      //   157	168	453	java/lang/Exception
      //   178	204	453	java/lang/Exception
      //   321	386	453	java/lang/Exception
      //   392	409	453	java/lang/Exception
      //   409	436	453	java/lang/Exception
      //   439	450	453	java/lang/Exception
      //   611	628	453	java/lang/Exception
      //   628	655	453	java/lang/Exception
      //   658	669	453	java/lang/Exception
      //   112	140	521	java/lang/InterruptedException
      //   148	157	521	java/lang/InterruptedException
      //   222	263	521	java/lang/InterruptedException
      //   477	518	521	java/lang/InterruptedException
      //   678	719	521	java/lang/InterruptedException
      //   719	722	521	java/lang/InterruptedException
      //   834	849	521	java/lang/InterruptedException
      //   905	920	521	java/lang/InterruptedException
      //   923	938	521	java/lang/InterruptedException
      //   548	558	579	java/lang/Exception
      //   563	568	579	java/lang/Exception
      //   573	578	579	java/lang/Exception
      //   157	168	672	finally
      //   178	204	672	finally
      //   321	386	672	finally
      //   392	409	672	finally
      //   409	436	672	finally
      //   439	450	672	finally
      //   455	473	672	finally
      //   611	628	672	finally
      //   628	655	672	finally
      //   658	669	672	finally
      //   112	140	722	java/lang/Exception
      //   148	157	722	java/lang/Exception
      //   222	263	722	java/lang/Exception
      //   477	518	722	java/lang/Exception
      //   678	719	722	java/lang/Exception
      //   719	722	722	java/lang/Exception
      //   834	849	722	java/lang/Exception
      //   905	920	722	java/lang/Exception
      //   923	938	722	java/lang/Exception
      //   775	783	802	java/lang/Exception
      //   787	791	802	java/lang/Exception
      //   796	801	802	java/lang/Exception
      //   112	140	852	finally
      //   148	157	852	finally
      //   222	263	852	finally
      //   477	518	852	finally
      //   678	719	852	finally
      //   719	722	852	finally
      //   834	849	852	finally
      //   905	920	852	finally
      //   923	938	852	finally
      //   876	884	941	java/lang/Exception
      //   888	892	941	java/lang/Exception
      //   897	902	941	java/lang/Exception
      //   276	286	975	java/lang/Exception
      //   291	296	975	java/lang/Exception
      //   301	306	975	java/lang/Exception
      //   539	543	1007	java/lang/Exception
      //   767	771	1012	java/lang/Exception
      //   868	872	1017	java/lang/Exception
      //   267	271	1022	java/lang/Exception
      //   9	27	1027	finally
      //   31	46	1027	finally
      //   50	73	1027	finally
      //   73	86	1027	finally
      //   734	763	1027	finally
      //   86	99	1032	finally
      //   99	112	1045	finally
      //   9	27	1059	java/lang/Exception
      //   31	46	1059	java/lang/Exception
      //   50	73	1059	java/lang/Exception
      //   73	86	1059	java/lang/Exception
      //   86	99	1071	java/lang/Exception
      //   99	112	1084	java/lang/Exception
      //   9	27	1098	java/lang/InterruptedException
      //   31	46	1098	java/lang/InterruptedException
      //   50	73	1098	java/lang/InterruptedException
      //   73	86	1098	java/lang/InterruptedException
      //   86	99	1112	java/lang/InterruptedException
      //   99	112	1127	java/lang/InterruptedException
    }
  }
}

/* Location:           /Users/mattshapiro/Downloads/dex2jar/com.dji.smartphone.downloader-dex2jar.jar
 * Qualified Name:     com.stericson.RootTools.Executer
 * JD-Core Version:    0.6.2
 */