package cn.jpush.android.service;

public final class n extends Thread
{
  private static final String[] z;
  boolean a = true;
  private volatile boolean c = false;

  static
  {
    Object localObject1 = new String[45];
    int i = 0;
    String str1 = "i|.9\017\fq52\023Iq.5\022B2.4\017Is>\025\031\f/z";
    int j = -1;
    Object localObject2 = localObject1;
    Object localObject3 = str1.toCharArray();
    int k = localObject3.length;
    int m = 0;
    label36: Object localObject4;
    int n;
    int i1;
    Object localObject5;
    label52: int i2;
    int i3;
    if (k <= 1)
    {
      localObject4 = localObject3;
      n = m;
      i1 = k;
      localObject5 = localObject3;
      i2 = localObject5[m];
      switch (n % 5)
      {
      default:
        i3 = 125;
      case 0:
      case 1:
      case 2:
      case 3:
      }
    }
    while (true)
    {
      localObject5[m] = ((char)(i3 ^ i2));
      m = n + 1;
      if (i1 == 0)
      {
        localObject5 = localObject4;
        n = m;
        m = i1;
        break label52;
      }
      k = i1;
      localObject3 = localObject4;
      if (k > m)
        break label36;
      String str2 = new String((char[])localObject3).intern();
      switch (j)
      {
      default:
        localObject1[i] = str2;
        i = 1;
        str1 = "~w9*@\tv";
        localObject1 = localObject2;
        j = 0;
        break;
      case 0:
        localObject1[i] = str2;
        i = 2;
        str1 = "|g)4.I`,5\036I";
        j = 1;
        localObject1 = localObject2;
        break;
      case 1:
        localObject1[i] = str2;
        i = 3;
        str1 = "e|3(@\tvP";
        j = 2;
        localObject1 = localObject2;
        break;
      case 2:
        localObject1[i] = str2;
        i = 4;
        str1 = "`}=5\023\ft;5\021Ivv|\tD`?=\031evza]";
        j = 3;
        localObject1 = localObject2;
        break;
      case 3:
        localObject1[i] = str2;
        i = 5;
        str1 = "`}=5\023\fa/?\036Iw>}]^w=5\016X`;(\024C|\023\030@";
        j = 4;
        localObject1 = localObject2;
        break;
      case 4:
        localObject1[i] = str2;
        i = 6;
        str1 = "e|3(][{.4]\0012";
        j = 5;
        localObject1 = localObject2;
        break;
      case 5:
        localObject1[i] = str2;
        i = 7;
        str1 = "O`?=\tI2)3\036Gw.|\033M~39\031\fe3(\025\ff2.\030Mv\0238]\0212";
        j = 6;
        localObject1 = localObject2;
        break;
      case 6:
        localObject1[i] = str2;
        i = 8;
        str1 = "O|t6\rYa2r\034Bv(3\024H<32\tI|.r>c\\\024\031>x[\025\022";
        j = 7;
        localObject1 = localObject2;
        break;
      case 7:
        localObject1[i] = str2;
        i = 9;
        str1 = "\f\n3\017X2g|";
        j = 8;
        localObject1 = localObject2;
        break;
      case 8:
        localObject1[i] = str2;
        i = 10;
        str1 = "\f2z|]\f\0223\016X(zqC\f";
        j = 9;
        localObject1 = localObject2;
        break;
      case 9:
        localObject1[i] = str2;
        i = 11;
        str1 = "`}=5\023\ft;5\021Iv`|";
        j = 10;
        localObject1 = localObject2;
        break;
      case 10:
        localObject1[i] = str2;
        i = 12;
        str1 = "h\\\tf]\001,z";
        j = 11;
        localObject1 = localObject2;
        break;
      case 11:
        localObject1[i] = str2;
        i = 13;
        str1 = "";
        j = 12;
        localObject1 = localObject2;
        break;
      case 12:
        localObject1[i] = str2;
        i = 14;
        str1 = "_}((\"Gw#|G\f";
        j = 13;
        localObject1 = localObject2;
        break;
      case 13:
        localObject1[i] = str2;
        i = 15;
        str1 = "@}=5\023ng<:\030^2g|";
        j = 14;
        localObject1 = localObject2;
        break;
      case 14:
        localObject1[i] = str2;
        i = 16;
        str1 = "\f?z";
        j = 15;
        localObject1 = localObject2;
        break;
      case 15:
        localObject1[i] = str2;
        i = 17;
        str1 = "^w.|@\f";
        j = 16;
        localObject1 = localObject2;
        break;
      case 16:
        localObject1[i] = str2;
        i = 18;
        str1 = "aVo";
        j = 17;
        localObject1 = localObject2;
        break;
      case 17:
        localObject1[i] = str2;
        i = 19;
        str1 = "";
        j = 18;
        localObject1 = localObject2;
        break;
      case 18:
        localObject1[i] = str2;
        i = 20;
        str1 = "\f/z";
        j = 19;
        localObject1 = localObject2;
        break;
      case 19:
        localObject1[i] = str2;
        i = 21;
        str1 = "\\s(/\030`w4|@\f";
        j = 20;
        localObject1 = localObject2;
        break;
      case 20:
        localObject1[i] = str2;
        i = 22;
        str1 = "\035<mrL";
        j = 21;
        localObject1 = localObject2;
        break;
      case 21:
        localObject1[i] = str2;
        i = 23;
        str1 = "@}=5\023\ft;5\021\f(z/\022^f\0057\030U2g|";
        j = 22;
        localObject1 = localObject2;
        break;
      case 22:
        localObject1[i] = str2;
        i = 24;
        str1 = "\f2z?\022A;2\031\f/z";
        j = 23;
        localObject1 = localObject2;
        break;
      case 23:
        localObject1[i] = str2;
        i = 25;
        str1 = "_{>|@\f";
        j = 24;
        localObject1 = localObject2;
        break;
      case 24:
        localObject1[i] = str2;
        i = 26;
        str1 = "\f2z(\022Xs6\020\030B2g|";
        j = 25;
        localObject1 = localObject2;
        break;
      case 25:
        localObject1[i] = str2;
        i = 27;
        str1 = "\f|5(]Ij3/\t_2`|\024Ba?.\t";
        j = 26;
        localObject1 = localObject2;
        break;
      case 26:
        localObject1[i] = str2;
        i = 28;
        str1 = "@}=5\023\ft;5\021\f(z\020\022K{4a";
        j = 27;
        localObject1 = localObject2;
        break;
      case 27:
        localObject1[i] = str2;
        i = 29;
        str1 = "\fq;2\023Cfz,\034^a?|\016I`,9\017x{79]";
        j = 28;
        localObject1 = localObject2;
        break;
      case 28:
        localObject1[i] = str2;
        i = 30;
        str1 = "@}=5\023s`?,\022^f\005(\024Aw";
        j = 29;
        localObject1 = localObject2;
        break;
      case 29:
        localObject1[i] = str2;
        i = 31;
        str1 = "\ff5(\022@^?2]\0212";
        j = 30;
        localObject1 = localObject2;
        break;
      case 30:
        localObject1[i] = str2;
        i = 32;
        str1 = "@}=5\023\ft;5\021\f(z(\022X}6\020\030B2g|";
        j = 31;
        localObject1 = localObject2;
        break;
      case 31:
        localObject1[i] = str2;
        i = 33;
        str1 = "p<";
        j = 32;
        localObject1 = localObject2;
        break;
      case 32:
        localObject1[i] = str2;
        i = 34;
        str1 = "_f(\027\030U2g|";
        j = 33;
        localObject1 = localObject2;
        break;
      case 33:
        localObject1[i] = str2;
        i = 35;
        str1 = "_d?.\016E}4|@\f";
        j = 34;
        localObject1 = localObject2;
        break;
      case 34:
        localObject1[i] = str2;
        i = 36;
        str1 = "_}((\"Gw#f";
        j = 35;
        localObject1 = localObject2;
        break;
      case 35:
        localObject1[i] = str2;
        i = 37;
        str1 = "@}=5\023sa?.\013I`\005(\024Aw";
        j = 36;
        localObject1 = localObject2;
        break;
      case 36:
        localObject1[i] = str2;
        i = 38;
        str1 = "\f2z|]\f2z|]\f~5;\024BM93\016X{79G\f";
        j = 37;
        localObject1 = localObject2;
        break;
      case 37:
        localObject1[i] = str2;
        i = 39;
        str1 = "\f{)|\030T{)(\016\f(z)\rHs.9";
        j = 38;
        localObject1 = localObject2;
        break;
      case 38:
        localObject1[i] = str2;
        i = 40;
        str1 = "\f2z|\017Ib5.\tx{79]\0212";
        j = 39;
        localObject1 = localObject2;
        break;
      case 39:
        localObject1[i] = str2;
        i = 41;
        str1 = "\t\"h\004";
        j = 40;
        localObject1 = localObject2;
        break;
      case 40:
        localObject1[i] = str2;
        i = 42;
        str1 = "_w(*\030^F31\030\f/z";
        j = 41;
        localObject1 = localObject2;
        break;
      case 41:
        localObject1[i] = str2;
        i = 43;
        str1 = "_f31\030\f/z";
        j = 42;
        localObject1 = localObject2;
        break;
      case 42:
        localObject1[i] = str2;
        i = 44;
        str1 = "`}=5\023\0217>V";
        j = 43;
        localObject1 = localObject2;
        break;
      case 43:
        localObject1[i] = str2;
        z = localObject2;
        return;
        i3 = 44;
        continue;
        i3 = 18;
        continue;
        i3 = 90;
        continue;
        i3 = 92;
      }
    }
  }

  public n(PushService paramPushService)
  {
  }

  // ERROR //
  private int a()
  {
    // Byte code:
    //   0: getstatic 119	cn/jpush/android/service/n:z	[Ljava/lang/String;
    //   3: bipush 18
    //   5: aaload
    //   6: invokestatic 137	java/security/MessageDigest:getInstance	(Ljava/lang/String;)Ljava/security/MessageDigest;
    //   9: getstatic 143	cn/jpush/android/service/PushService:t	Ljava/lang/String;
    //   12: invokevirtual 147	java/lang/String:getBytes	()[B
    //   15: invokevirtual 151	java/security/MessageDigest:digest	([B)[B
    //   18: astore_1
    //   19: new 153	java/lang/StringBuilder
    //   22: dup
    //   23: iconst_2
    //   24: aload_1
    //   25: arraylength
    //   26: imul
    //   27: invokespecial 156	java/lang/StringBuilder:<init>	(I)V
    //   30: astore_2
    //   31: aload_1
    //   32: arraylength
    //   33: istore_3
    //   34: iconst_0
    //   35: istore 4
    //   37: iload 4
    //   39: iload_3
    //   40: if_icmpge +50 -> 90
    //   43: aload_1
    //   44: iload 4
    //   46: baload
    //   47: istore 78
    //   49: getstatic 119	cn/jpush/android/service/n:z	[Ljava/lang/String;
    //   52: bipush 41
    //   54: aaload
    //   55: astore 79
    //   57: iconst_1
    //   58: anewarray 158	java/lang/Object
    //   61: astore 80
    //   63: aload 80
    //   65: iconst_0
    //   66: iload 78
    //   68: invokestatic 164	java/lang/Byte:valueOf	(B)Ljava/lang/Byte;
    //   71: aastore
    //   72: aload_2
    //   73: aload 79
    //   75: aload 80
    //   77: invokestatic 168	java/lang/String:format	(Ljava/lang/String;[Ljava/lang/Object;)Ljava/lang/String;
    //   80: invokevirtual 172	java/lang/StringBuilder:append	(Ljava/lang/String;)Ljava/lang/StringBuilder;
    //   83: pop
    //   84: iinc 4 1
    //   87: goto -50 -> 37
    //   90: aload_2
    //   91: invokevirtual 175	java/lang/StringBuilder:toString	()Ljava/lang/String;
    //   94: astore 5
    //   96: getstatic 119	cn/jpush/android/service/n:z	[Ljava/lang/String;
    //   99: bipush 19
    //   101: aaload
    //   102: astore 6
    //   104: iconst_2
    //   105: anewarray 158	java/lang/Object
    //   108: astore 7
    //   110: aload 7
    //   112: iconst_0
    //   113: getstatic 179	cn/jpush/android/service/PushService:s	J
    //   116: invokestatic 184	java/lang/Long:valueOf	(J)Ljava/lang/Long;
    //   119: aastore
    //   120: aload 7
    //   122: iconst_1
    //   123: aload 5
    //   125: aastore
    //   126: aload 6
    //   128: aload 7
    //   130: invokestatic 168	java/lang/String:format	(Ljava/lang/String;[Ljava/lang/Object;)Ljava/lang/String;
    //   133: pop
    //   134: invokestatic 188	cn/jpush/android/util/x:c	()V
    //   137: getstatic 119	cn/jpush/android/service/n:z	[Ljava/lang/String;
    //   140: bipush 22
    //   142: aaload
    //   143: getstatic 119	cn/jpush/android/service/n:z	[Ljava/lang/String;
    //   146: bipush 33
    //   148: aaload
    //   149: invokevirtual 192	java/lang/String:split	(Ljava/lang/String;)[Ljava/lang/String;
    //   152: astore 9
    //   154: aload 9
    //   156: iconst_0
    //   157: aaload
    //   158: invokestatic 198	java/lang/Integer:parseInt	(Ljava/lang/String;)I
    //   161: bipush 16
    //   163: ishl
    //   164: aload 9
    //   166: iconst_1
    //   167: aaload
    //   168: invokestatic 198	java/lang/Integer:parseInt	(Ljava/lang/String;)I
    //   171: bipush 8
    //   173: ishl
    //   174: iadd
    //   175: aload 9
    //   177: iconst_2
    //   178: aaload
    //   179: invokestatic 198	java/lang/Integer:parseInt	(Ljava/lang/String;)I
    //   182: iadd
    //   183: istore 10
    //   185: new 153	java/lang/StringBuilder
    //   188: dup
    //   189: getstatic 203	cn/jpush/android/a:f	Ljava/lang/String;
    //   192: invokevirtual 206	java/lang/String:length	()I
    //   195: invokespecial 156	java/lang/StringBuilder:<init>	(I)V
    //   198: astore 11
    //   200: aload 11
    //   202: getstatic 203	cn/jpush/android/a:f	Ljava/lang/String;
    //   205: invokevirtual 172	java/lang/StringBuilder:append	(Ljava/lang/String;)Ljava/lang/StringBuilder;
    //   208: pop
    //   209: aload 11
    //   211: invokevirtual 175	java/lang/StringBuilder:toString	()Ljava/lang/String;
    //   214: astore 13
    //   216: aload_0
    //   217: getfield 122	cn/jpush/android/service/n:b	Lcn/jpush/android/service/PushService;
    //   220: getfield 210	cn/jpush/android/service/PushService:v	I
    //   223: ifeq +1369 -> 1592
    //   226: invokestatic 188	cn/jpush/android/util/x:c	()V
    //   229: aload_0
    //   230: getfield 122	cn/jpush/android/service/n:b	Lcn/jpush/android/service/PushService;
    //   233: invokevirtual 214	cn/jpush/android/service/PushService:getApplicationContext	()Landroid/content/Context;
    //   236: invokestatic 220	cn/jpush/android/util/a:w	(Landroid/content/Context;)Ljava/lang/String;
    //   239: astore 18
    //   241: sipush 128
    //   244: newarray byte
    //   246: astore 19
    //   248: invokestatic 226	java/lang/System:currentTimeMillis	()J
    //   251: lstore 20
    //   253: aload_0
    //   254: getfield 122	cn/jpush/android/service/n:b	Lcn/jpush/android/service/PushService;
    //   257: getfield 210	cn/jpush/android/service/PushService:v	I
    //   260: aload 19
    //   262: getstatic 179	cn/jpush/android/service/PushService:s	J
    //   265: aload 5
    //   267: aload 13
    //   269: iload 10
    //   271: i2l
    //   272: invokestatic 232	cn/jpush/android/service/PushProtocol:LogPushWithBack	(I[BJLjava/lang/String;Ljava/lang/String;J)I
    //   275: istore 22
    //   277: new 153	java/lang/StringBuilder
    //   280: dup
    //   281: invokespecial 233	java/lang/StringBuilder:<init>	()V
    //   284: aload 18
    //   286: invokevirtual 172	java/lang/StringBuilder:append	(Ljava/lang/String;)Ljava/lang/StringBuilder;
    //   289: ldc 235
    //   291: invokevirtual 172	java/lang/StringBuilder:append	(Ljava/lang/String;)Ljava/lang/StringBuilder;
    //   294: iload 22
    //   296: invokevirtual 238	java/lang/StringBuilder:append	(I)Ljava/lang/StringBuilder;
    //   299: ldc 235
    //   301: invokevirtual 172	java/lang/StringBuilder:append	(Ljava/lang/String;)Ljava/lang/StringBuilder;
    //   304: invokestatic 240	cn/jpush/android/service/PushService:b	()Ljava/lang/String;
    //   307: invokevirtual 172	java/lang/StringBuilder:append	(Ljava/lang/String;)Ljava/lang/StringBuilder;
    //   310: ldc 235
    //   312: invokevirtual 172	java/lang/StringBuilder:append	(Ljava/lang/String;)Ljava/lang/StringBuilder;
    //   315: invokestatic 243	cn/jpush/android/util/a:d	()Ljava/lang/String;
    //   318: invokevirtual 172	java/lang/StringBuilder:append	(Ljava/lang/String;)Ljava/lang/StringBuilder;
    //   321: invokevirtual 175	java/lang/StringBuilder:toString	()Ljava/lang/String;
    //   324: astore 23
    //   326: invokestatic 226	java/lang/System:currentTimeMillis	()J
    //   329: lstore 24
    //   331: lload 24
    //   333: lload 20
    //   335: lsub
    //   336: lstore 26
    //   338: new 153	java/lang/StringBuilder
    //   341: dup
    //   342: getstatic 119	cn/jpush/android/service/n:z	[Ljava/lang/String;
    //   345: bipush 14
    //   347: aaload
    //   348: invokespecial 246	java/lang/StringBuilder:<init>	(Ljava/lang/String;)V
    //   351: aload 23
    //   353: invokevirtual 172	java/lang/StringBuilder:append	(Ljava/lang/String;)Ljava/lang/StringBuilder;
    //   356: getstatic 119	cn/jpush/android/service/n:z	[Ljava/lang/String;
    //   359: bipush 38
    //   361: aaload
    //   362: invokevirtual 172	java/lang/StringBuilder:append	(Ljava/lang/String;)Ljava/lang/StringBuilder;
    //   365: lload 24
    //   367: invokevirtual 249	java/lang/StringBuilder:append	(J)Ljava/lang/StringBuilder;
    //   370: getstatic 119	cn/jpush/android/service/n:z	[Ljava/lang/String;
    //   373: bipush 16
    //   375: aaload
    //   376: invokevirtual 172	java/lang/StringBuilder:append	(Ljava/lang/String;)Ljava/lang/StringBuilder;
    //   379: lload 20
    //   381: invokevirtual 249	java/lang/StringBuilder:append	(J)Ljava/lang/StringBuilder;
    //   384: getstatic 119	cn/jpush/android/service/n:z	[Ljava/lang/String;
    //   387: bipush 20
    //   389: aaload
    //   390: invokevirtual 172	java/lang/StringBuilder:append	(Ljava/lang/String;)Ljava/lang/StringBuilder;
    //   393: lload 26
    //   395: invokevirtual 249	java/lang/StringBuilder:append	(J)Ljava/lang/StringBuilder;
    //   398: invokevirtual 175	java/lang/StringBuilder:toString	()Ljava/lang/String;
    //   401: pop
    //   402: invokestatic 188	cn/jpush/android/util/x:c	()V
    //   405: iload 22
    //   407: ifeq +11 -> 418
    //   410: iload 22
    //   412: sipush 9999
    //   415: if_icmpne +992 -> 1407
    //   418: aload 19
    //   420: invokestatic 252	cn/jpush/android/util/a:b	([B)I
    //   423: istore 29
    //   425: aload 19
    //   427: invokestatic 254	cn/jpush/android/util/a:c	([B)I
    //   430: istore 30
    //   432: new 153	java/lang/StringBuilder
    //   435: dup
    //   436: getstatic 119	cn/jpush/android/service/n:z	[Ljava/lang/String;
    //   439: bipush 17
    //   441: aaload
    //   442: invokespecial 246	java/lang/StringBuilder:<init>	(Ljava/lang/String;)V
    //   445: iload 22
    //   447: invokevirtual 238	java/lang/StringBuilder:append	(I)Ljava/lang/StringBuilder;
    //   450: getstatic 119	cn/jpush/android/service/n:z	[Ljava/lang/String;
    //   453: bipush 24
    //   455: aaload
    //   456: invokevirtual 172	java/lang/StringBuilder:append	(Ljava/lang/String;)Ljava/lang/StringBuilder;
    //   459: iload 29
    //   461: invokevirtual 238	java/lang/StringBuilder:append	(I)Ljava/lang/StringBuilder;
    //   464: getstatic 119	cn/jpush/android/service/n:z	[Ljava/lang/String;
    //   467: bipush 31
    //   469: aaload
    //   470: invokevirtual 172	java/lang/StringBuilder:append	(Ljava/lang/String;)Ljava/lang/StringBuilder;
    //   473: iload 30
    //   475: invokevirtual 238	java/lang/StringBuilder:append	(I)Ljava/lang/StringBuilder;
    //   478: invokevirtual 175	java/lang/StringBuilder:toString	()Ljava/lang/String;
    //   481: pop
    //   482: invokestatic 256	cn/jpush/android/util/x:d	()V
    //   485: new 153	java/lang/StringBuilder
    //   488: dup
    //   489: getstatic 119	cn/jpush/android/service/n:z	[Ljava/lang/String;
    //   492: bipush 15
    //   494: aaload
    //   495: invokespecial 246	java/lang/StringBuilder:<init>	(Ljava/lang/String;)V
    //   498: aload 19
    //   500: iload 30
    //   502: invokestatic 259	cn/jpush/android/service/PushService:a	([BI)Ljava/lang/String;
    //   505: invokevirtual 172	java/lang/StringBuilder:append	(Ljava/lang/String;)Ljava/lang/StringBuilder;
    //   508: invokevirtual 175	java/lang/StringBuilder:toString	()Ljava/lang/String;
    //   511: pop
    //   512: invokestatic 256	cn/jpush/android/util/x:d	()V
    //   515: iload 30
    //   517: bipush 34
    //   519: if_icmpge +41 -> 560
    //   522: getstatic 119	cn/jpush/android/service/n:z	[Ljava/lang/String;
    //   525: iconst_2
    //   526: aaload
    //   527: new 153	java/lang/StringBuilder
    //   530: dup
    //   531: getstatic 119	cn/jpush/android/service/n:z	[Ljava/lang/String;
    //   534: bipush 32
    //   536: aaload
    //   537: invokespecial 246	java/lang/StringBuilder:<init>	(Ljava/lang/String;)V
    //   540: iload 30
    //   542: invokevirtual 238	java/lang/StringBuilder:append	(I)Ljava/lang/StringBuilder;
    //   545: getstatic 119	cn/jpush/android/service/n:z	[Ljava/lang/String;
    //   548: bipush 29
    //   550: aaload
    //   551: invokevirtual 172	java/lang/StringBuilder:append	(Ljava/lang/String;)Ljava/lang/StringBuilder;
    //   554: invokevirtual 175	java/lang/StringBuilder:toString	()Ljava/lang/String;
    //   557: invokestatic 263	cn/jpush/android/util/x:e	(Ljava/lang/String;Ljava/lang/String;)V
    //   560: iconst_0
    //   561: istore 33
    //   563: iconst_0
    //   564: istore 34
    //   566: iload 34
    //   568: iconst_2
    //   569: if_icmpge +29 -> 598
    //   572: iload 33
    //   574: bipush 8
    //   576: ishl
    //   577: sipush 255
    //   580: aload 19
    //   582: iload 34
    //   584: bipush 20
    //   586: iadd
    //   587: baload
    //   588: iand
    //   589: iadd
    //   590: istore 33
    //   592: iinc 34 1
    //   595: goto -29 -> 566
    //   598: iload 33
    //   600: ifne +434 -> 1034
    //   603: lconst_0
    //   604: lstore 56
    //   606: iconst_0
    //   607: istore 58
    //   609: iload 58
    //   611: iconst_4
    //   612: if_icmpge +30 -> 642
    //   615: lload 56
    //   617: bipush 8
    //   619: lshl
    //   620: sipush 255
    //   623: aload 19
    //   625: iload 58
    //   627: bipush 22
    //   629: iadd
    //   630: baload
    //   631: iand
    //   632: i2l
    //   633: ladd
    //   634: lstore 56
    //   636: iinc 58 1
    //   639: goto -30 -> 609
    //   642: new 153	java/lang/StringBuilder
    //   645: dup
    //   646: getstatic 119	cn/jpush/android/service/n:z	[Ljava/lang/String;
    //   649: bipush 25
    //   651: aaload
    //   652: invokespecial 246	java/lang/StringBuilder:<init>	(Ljava/lang/String;)V
    //   655: lload 56
    //   657: invokevirtual 249	java/lang/StringBuilder:append	(J)Ljava/lang/StringBuilder;
    //   660: invokevirtual 175	java/lang/StringBuilder:toString	()Ljava/lang/String;
    //   663: pop
    //   664: invokestatic 256	cn/jpush/android/util/x:d	()V
    //   667: iconst_0
    //   668: istore 60
    //   670: iconst_0
    //   671: istore 61
    //   673: iload 61
    //   675: iconst_2
    //   676: if_icmpge +29 -> 705
    //   679: iload 60
    //   681: bipush 8
    //   683: ishl
    //   684: sipush 255
    //   687: aload 19
    //   689: iload 61
    //   691: bipush 26
    //   693: iadd
    //   694: baload
    //   695: iand
    //   696: iadd
    //   697: istore 60
    //   699: iinc 61 1
    //   702: goto -29 -> 673
    //   705: new 153	java/lang/StringBuilder
    //   708: dup
    //   709: getstatic 119	cn/jpush/android/service/n:z	[Ljava/lang/String;
    //   712: bipush 35
    //   714: aaload
    //   715: invokespecial 246	java/lang/StringBuilder:<init>	(Ljava/lang/String;)V
    //   718: iload 60
    //   720: invokevirtual 238	java/lang/StringBuilder:append	(I)Ljava/lang/StringBuilder;
    //   723: invokevirtual 175	java/lang/StringBuilder:toString	()Ljava/lang/String;
    //   726: pop
    //   727: invokestatic 256	cn/jpush/android/util/x:d	()V
    //   730: iconst_0
    //   731: istore 63
    //   733: iconst_0
    //   734: istore 64
    //   736: iload 63
    //   738: iconst_2
    //   739: if_icmpge +33 -> 772
    //   742: iload 64
    //   744: bipush 8
    //   746: ishl
    //   747: sipush 255
    //   750: aload 19
    //   752: iload 63
    //   754: bipush 28
    //   756: iadd
    //   757: baload
    //   758: iand
    //   759: iadd
    //   760: istore 76
    //   762: iinc 63 1
    //   765: iload 76
    //   767: istore 64
    //   769: goto -33 -> 736
    //   772: iload 64
    //   774: newarray byte
    //   776: astore 65
    //   778: iconst_0
    //   779: istore 66
    //   781: iload 66
    //   783: aload 65
    //   785: arraylength
    //   786: if_icmpge +27 -> 813
    //   789: aload 65
    //   791: iload 66
    //   793: sipush 255
    //   796: aload 19
    //   798: iload 66
    //   800: bipush 30
    //   802: iadd
    //   803: baload
    //   804: iand
    //   805: i2b
    //   806: bastore
    //   807: iinc 66 1
    //   810: goto -29 -> 781
    //   813: new 15	java/lang/String
    //   816: dup
    //   817: aload 65
    //   819: invokespecial 266	java/lang/String:<init>	([B)V
    //   822: astore 67
    //   824: new 153	java/lang/StringBuilder
    //   827: dup
    //   828: getstatic 119	cn/jpush/android/service/n:z	[Ljava/lang/String;
    //   831: bipush 34
    //   833: aaload
    //   834: invokespecial 246	java/lang/StringBuilder:<init>	(Ljava/lang/String;)V
    //   837: aload 67
    //   839: invokevirtual 172	java/lang/StringBuilder:append	(Ljava/lang/String;)Ljava/lang/StringBuilder;
    //   842: invokevirtual 175	java/lang/StringBuilder:toString	()Ljava/lang/String;
    //   845: pop
    //   846: invokestatic 256	cn/jpush/android/util/x:d	()V
    //   849: iload 64
    //   851: bipush 30
    //   853: iadd
    //   854: istore 69
    //   856: lconst_0
    //   857: lstore 70
    //   859: iconst_0
    //   860: istore 72
    //   862: iload 72
    //   864: iconst_4
    //   865: if_icmpge +30 -> 895
    //   868: lload 70
    //   870: bipush 8
    //   872: lshl
    //   873: sipush 255
    //   876: aload 19
    //   878: iload 69
    //   880: iload 72
    //   882: iadd
    //   883: baload
    //   884: iand
    //   885: i2l
    //   886: ladd
    //   887: lstore 70
    //   889: iinc 72 1
    //   892: goto -30 -> 862
    //   895: iload 69
    //   897: iconst_4
    //   898: iadd
    //   899: istore 73
    //   901: iload 73
    //   903: iload 30
    //   905: if_icmpne +460 -> 1365
    //   908: invokestatic 256	cn/jpush/android/util/x:d	()V
    //   911: lload 70
    //   913: putstatic 269	cn/jpush/android/service/PushService:m	J
    //   916: invokestatic 226	java/lang/System:currentTimeMillis	()J
    //   919: ldc2_w 270
    //   922: ldiv
    //   923: putstatic 274	cn/jpush/android/service/PushService:n	J
    //   926: getstatic 119	cn/jpush/android/service/n:z	[Ljava/lang/String;
    //   929: iconst_2
    //   930: aaload
    //   931: new 153	java/lang/StringBuilder
    //   934: dup
    //   935: getstatic 119	cn/jpush/android/service/n:z	[Ljava/lang/String;
    //   938: bipush 43
    //   940: aaload
    //   941: invokespecial 246	java/lang/StringBuilder:<init>	(Ljava/lang/String;)V
    //   944: lload 70
    //   946: invokevirtual 249	java/lang/StringBuilder:append	(J)Ljava/lang/StringBuilder;
    //   949: invokevirtual 175	java/lang/StringBuilder:toString	()Ljava/lang/String;
    //   952: invokestatic 276	cn/jpush/android/util/x:c	(Ljava/lang/String;Ljava/lang/String;)V
    //   955: new 153	java/lang/StringBuilder
    //   958: dup
    //   959: getstatic 119	cn/jpush/android/service/n:z	[Ljava/lang/String;
    //   962: bipush 42
    //   964: aaload
    //   965: invokespecial 246	java/lang/StringBuilder:<init>	(Ljava/lang/String;)V
    //   968: getstatic 269	cn/jpush/android/service/PushService:m	J
    //   971: invokevirtual 249	java/lang/StringBuilder:append	(J)Ljava/lang/StringBuilder;
    //   974: getstatic 119	cn/jpush/android/service/n:z	[Ljava/lang/String;
    //   977: bipush 40
    //   979: aaload
    //   980: invokevirtual 172	java/lang/StringBuilder:append	(Ljava/lang/String;)Ljava/lang/StringBuilder;
    //   983: getstatic 274	cn/jpush/android/service/PushService:n	J
    //   986: invokevirtual 249	java/lang/StringBuilder:append	(J)Ljava/lang/StringBuilder;
    //   989: invokevirtual 175	java/lang/StringBuilder:toString	()Ljava/lang/String;
    //   992: pop
    //   993: invokestatic 188	cn/jpush/android/util/x:c	()V
    //   996: aload_0
    //   997: getfield 122	cn/jpush/android/service/n:b	Lcn/jpush/android/service/PushService;
    //   1000: invokevirtual 214	cn/jpush/android/service/PushService:getApplicationContext	()Landroid/content/Context;
    //   1003: getstatic 119	cn/jpush/android/service/n:z	[Ljava/lang/String;
    //   1006: bipush 37
    //   1008: aaload
    //   1009: getstatic 269	cn/jpush/android/service/PushService:m	J
    //   1012: invokestatic 281	cn/jpush/android/util/ae:b	(Landroid/content/Context;Ljava/lang/String;J)V
    //   1015: aload_0
    //   1016: getfield 122	cn/jpush/android/service/n:b	Lcn/jpush/android/service/PushService;
    //   1019: invokevirtual 214	cn/jpush/android/service/PushService:getApplicationContext	()Landroid/content/Context;
    //   1022: getstatic 119	cn/jpush/android/service/n:z	[Ljava/lang/String;
    //   1025: bipush 30
    //   1027: aaload
    //   1028: getstatic 274	cn/jpush/android/service/PushService:n	J
    //   1031: invokestatic 281	cn/jpush/android/util/ae:b	(Landroid/content/Context;Ljava/lang/String;J)V
    //   1034: iconst_0
    //   1035: istore 35
    //   1037: invokestatic 256	cn/jpush/android/util/x:d	()V
    //   1040: iconst_0
    //   1041: istore 36
    //   1043: iconst_0
    //   1044: istore 37
    //   1046: iconst_0
    //   1047: istore 38
    //   1049: iload 35
    //   1051: ifne +76 -> 1127
    //   1054: lload 26
    //   1056: ldc2_w 270
    //   1059: lcmp
    //   1060: istore 52
    //   1062: iconst_0
    //   1063: istore 36
    //   1065: iload 52
    //   1067: ifgt +6 -> 1073
    //   1070: iconst_1
    //   1071: istore 36
    //   1073: lload 26
    //   1075: ldc2_w 270
    //   1078: lcmp
    //   1079: istore 53
    //   1081: iconst_0
    //   1082: istore 37
    //   1084: iload 53
    //   1086: ifle +22 -> 1108
    //   1089: lload 26
    //   1091: ldc2_w 282
    //   1094: lcmp
    //   1095: istore 55
    //   1097: iconst_0
    //   1098: istore 37
    //   1100: iload 55
    //   1102: ifgt +6 -> 1108
    //   1105: iconst_1
    //   1106: istore 37
    //   1108: lload 26
    //   1110: ldc2_w 282
    //   1113: lcmp
    //   1114: istore 54
    //   1116: iconst_0
    //   1117: istore 38
    //   1119: iload 54
    //   1121: ifle +6 -> 1127
    //   1124: iconst_1
    //   1125: istore 38
    //   1127: new 285	cn/jpush/android/data/u
    //   1130: dup
    //   1131: aload_0
    //   1132: getfield 122	cn/jpush/android/service/n:b	Lcn/jpush/android/service/PushService;
    //   1135: invokevirtual 214	cn/jpush/android/service/PushService:getApplicationContext	()Landroid/content/Context;
    //   1138: invokespecial 288	cn/jpush/android/data/u:<init>	(Landroid/content/Context;)V
    //   1141: astore 39
    //   1143: aload 39
    //   1145: ifnull +179 -> 1324
    //   1148: aload 39
    //   1150: invokevirtual 290	cn/jpush/android/data/u:a	()V
    //   1153: aload 39
    //   1155: aload 23
    //   1157: invokevirtual 293	cn/jpush/android/data/u:a	(Ljava/lang/String;)Z
    //   1160: ifeq +354 -> 1514
    //   1163: new 153	java/lang/StringBuilder
    //   1166: dup
    //   1167: getstatic 119	cn/jpush/android/service/n:z	[Ljava/lang/String;
    //   1170: bipush 36
    //   1172: aaload
    //   1173: invokespecial 246	java/lang/StringBuilder:<init>	(Ljava/lang/String;)V
    //   1176: aload 23
    //   1178: invokevirtual 172	java/lang/StringBuilder:append	(Ljava/lang/String;)Ljava/lang/StringBuilder;
    //   1181: getstatic 119	cn/jpush/android/service/n:z	[Ljava/lang/String;
    //   1184: bipush 39
    //   1186: aaload
    //   1187: invokevirtual 172	java/lang/StringBuilder:append	(Ljava/lang/String;)Ljava/lang/StringBuilder;
    //   1190: invokevirtual 175	java/lang/StringBuilder:toString	()Ljava/lang/String;
    //   1193: pop
    //   1194: invokestatic 256	cn/jpush/android/util/x:d	()V
    //   1197: aload 39
    //   1199: aload 23
    //   1201: invokevirtual 296	cn/jpush/android/data/u:b	(Ljava/lang/String;)Landroid/database/Cursor;
    //   1204: astore 48
    //   1206: aload 48
    //   1208: astore 47
    //   1210: aload 47
    //   1212: ifnonnull +6 -> 1218
    //   1215: invokestatic 298	cn/jpush/android/util/x:e	()V
    //   1218: aload 47
    //   1220: invokestatic 301	cn/jpush/android/data/u:a	(Landroid/database/Cursor;)Lcn/jpush/android/data/w;
    //   1223: astore 50
    //   1225: aload 50
    //   1227: ifnull +240 -> 1467
    //   1230: aload 39
    //   1232: aload 23
    //   1234: aload 18
    //   1236: invokestatic 240	cn/jpush/android/service/PushService:b	()Ljava/lang/String;
    //   1239: invokestatic 243	cn/jpush/android/util/a:d	()Ljava/lang/String;
    //   1242: new 153	java/lang/StringBuilder
    //   1245: dup
    //   1246: invokespecial 233	java/lang/StringBuilder:<init>	()V
    //   1249: iload 22
    //   1251: invokevirtual 238	java/lang/StringBuilder:append	(I)Ljava/lang/StringBuilder;
    //   1254: invokevirtual 175	java/lang/StringBuilder:toString	()Ljava/lang/String;
    //   1257: iload 35
    //   1259: aload 50
    //   1261: invokevirtual 305	cn/jpush/android/data/w:f	()I
    //   1264: iadd
    //   1265: iconst_1
    //   1266: aload 50
    //   1268: invokevirtual 308	cn/jpush/android/data/w:g	()I
    //   1271: iadd
    //   1272: iload 36
    //   1274: aload 50
    //   1276: invokevirtual 311	cn/jpush/android/data/w:h	()I
    //   1279: iadd
    //   1280: iload 37
    //   1282: aload 50
    //   1284: invokevirtual 314	cn/jpush/android/data/w:i	()I
    //   1287: iadd
    //   1288: iload 38
    //   1290: aload 50
    //   1292: invokevirtual 317	cn/jpush/android/data/w:j	()I
    //   1295: iadd
    //   1296: iconst_0
    //   1297: aload 50
    //   1299: invokevirtual 320	cn/jpush/android/data/w:k	()I
    //   1302: iadd
    //   1303: invokevirtual 323	cn/jpush/android/data/u:b	(Ljava/lang/String;Ljava/lang/String;Ljava/lang/String;Ljava/lang/String;Ljava/lang/String;IIIIII)Z
    //   1306: pop
    //   1307: aload 47
    //   1309: ifnull +10 -> 1319
    //   1312: aload 47
    //   1314: invokeinterface 328 1 0
    //   1319: aload 39
    //   1321: invokevirtual 330	cn/jpush/android/data/u:b	()V
    //   1324: iload 22
    //   1326: istore 14
    //   1328: getstatic 119	cn/jpush/android/service/n:z	[Ljava/lang/String;
    //   1331: bipush 44
    //   1333: aaload
    //   1334: astore 15
    //   1336: iconst_1
    //   1337: anewarray 158	java/lang/Object
    //   1340: astore 16
    //   1342: aload 16
    //   1344: iconst_0
    //   1345: iload 14
    //   1347: invokestatic 333	java/lang/Integer:valueOf	(I)Ljava/lang/Integer;
    //   1350: aastore
    //   1351: aload 15
    //   1353: aload 16
    //   1355: invokestatic 168	java/lang/String:format	(Ljava/lang/String;[Ljava/lang/Object;)Ljava/lang/String;
    //   1358: pop
    //   1359: invokestatic 188	cn/jpush/android/util/x:c	()V
    //   1362: iload 14
    //   1364: ireturn
    //   1365: new 153	java/lang/StringBuilder
    //   1368: dup
    //   1369: getstatic 119	cn/jpush/android/service/n:z	[Ljava/lang/String;
    //   1372: bipush 21
    //   1374: aaload
    //   1375: invokespecial 246	java/lang/StringBuilder:<init>	(Ljava/lang/String;)V
    //   1378: iload 73
    //   1380: invokevirtual 238	java/lang/StringBuilder:append	(I)Ljava/lang/StringBuilder;
    //   1383: getstatic 119	cn/jpush/android/service/n:z	[Ljava/lang/String;
    //   1386: bipush 26
    //   1388: aaload
    //   1389: invokevirtual 172	java/lang/StringBuilder:append	(Ljava/lang/String;)Ljava/lang/StringBuilder;
    //   1392: iload 30
    //   1394: invokevirtual 238	java/lang/StringBuilder:append	(I)Ljava/lang/StringBuilder;
    //   1397: invokevirtual 175	java/lang/StringBuilder:toString	()Ljava/lang/String;
    //   1400: pop
    //   1401: invokestatic 256	cn/jpush/android/util/x:d	()V
    //   1404: goto -493 -> 911
    //   1407: iconst_1
    //   1408: istore 35
    //   1410: getstatic 119	cn/jpush/android/service/n:z	[Ljava/lang/String;
    //   1413: iconst_2
    //   1414: aaload
    //   1415: new 153	java/lang/StringBuilder
    //   1418: dup
    //   1419: getstatic 119	cn/jpush/android/service/n:z	[Ljava/lang/String;
    //   1422: bipush 28
    //   1424: aaload
    //   1425: invokespecial 246	java/lang/StringBuilder:<init>	(Ljava/lang/String;)V
    //   1428: iload 22
    //   1430: invokevirtual 238	java/lang/StringBuilder:append	(I)Ljava/lang/StringBuilder;
    //   1433: invokevirtual 175	java/lang/StringBuilder:toString	()Ljava/lang/String;
    //   1436: invokestatic 263	cn/jpush/android/util/x:e	(Ljava/lang/String;Ljava/lang/String;)V
    //   1439: new 153	java/lang/StringBuilder
    //   1442: dup
    //   1443: getstatic 119	cn/jpush/android/service/n:z	[Ljava/lang/String;
    //   1446: bipush 23
    //   1448: aaload
    //   1449: invokespecial 246	java/lang/StringBuilder:<init>	(Ljava/lang/String;)V
    //   1452: aload 23
    //   1454: invokevirtual 172	java/lang/StringBuilder:append	(Ljava/lang/String;)Ljava/lang/StringBuilder;
    //   1457: invokevirtual 175	java/lang/StringBuilder:toString	()Ljava/lang/String;
    //   1460: pop
    //   1461: invokestatic 188	cn/jpush/android/util/x:c	()V
    //   1464: goto -427 -> 1037
    //   1467: invokestatic 298	cn/jpush/android/util/x:e	()V
    //   1470: goto -163 -> 1307
    //   1473: astore 49
    //   1475: aload 47
    //   1477: astore 45
    //   1479: aload 45
    //   1481: ifnull -162 -> 1319
    //   1484: aload 45
    //   1486: invokeinterface 328 1 0
    //   1491: goto -172 -> 1319
    //   1494: astore 46
    //   1496: aconst_null
    //   1497: astore 47
    //   1499: aload 47
    //   1501: ifnull +10 -> 1511
    //   1504: aload 47
    //   1506: invokeinterface 328 1 0
    //   1511: aload 46
    //   1513: athrow
    //   1514: new 153	java/lang/StringBuilder
    //   1517: dup
    //   1518: getstatic 119	cn/jpush/android/service/n:z	[Ljava/lang/String;
    //   1521: bipush 36
    //   1523: aaload
    //   1524: invokespecial 246	java/lang/StringBuilder:<init>	(Ljava/lang/String;)V
    //   1527: aload 23
    //   1529: invokevirtual 172	java/lang/StringBuilder:append	(Ljava/lang/String;)Ljava/lang/StringBuilder;
    //   1532: getstatic 119	cn/jpush/android/service/n:z	[Ljava/lang/String;
    //   1535: bipush 27
    //   1537: aaload
    //   1538: invokevirtual 172	java/lang/StringBuilder:append	(Ljava/lang/String;)Ljava/lang/StringBuilder;
    //   1541: invokevirtual 175	java/lang/StringBuilder:toString	()Ljava/lang/String;
    //   1544: pop
    //   1545: invokestatic 256	cn/jpush/android/util/x:d	()V
    //   1548: aload 39
    //   1550: aload 23
    //   1552: aload 18
    //   1554: invokestatic 240	cn/jpush/android/service/PushService:b	()Ljava/lang/String;
    //   1557: invokestatic 243	cn/jpush/android/util/a:d	()Ljava/lang/String;
    //   1560: new 153	java/lang/StringBuilder
    //   1563: dup
    //   1564: invokespecial 233	java/lang/StringBuilder:<init>	()V
    //   1567: iload 22
    //   1569: invokevirtual 238	java/lang/StringBuilder:append	(I)Ljava/lang/StringBuilder;
    //   1572: invokevirtual 175	java/lang/StringBuilder:toString	()Ljava/lang/String;
    //   1575: iload 35
    //   1577: iconst_1
    //   1578: iload 36
    //   1580: iload 37
    //   1582: iload 38
    //   1584: iconst_0
    //   1585: invokevirtual 336	cn/jpush/android/data/u:a	(Ljava/lang/String;Ljava/lang/String;Ljava/lang/String;Ljava/lang/String;Ljava/lang/String;IIIIII)J
    //   1588: pop2
    //   1589: goto -270 -> 1319
    //   1592: iconst_m1
    //   1593: istore 14
    //   1595: goto -267 -> 1328
    //   1598: astore 46
    //   1600: goto -101 -> 1499
    //   1603: astore 44
    //   1605: aconst_null
    //   1606: astore 45
    //   1608: goto -129 -> 1479
    //
    // Exception table:
    //   from	to	target	type
    //   1215	1218	1473	java/lang/Exception
    //   1218	1225	1473	java/lang/Exception
    //   1230	1307	1473	java/lang/Exception
    //   1467	1470	1473	java/lang/Exception
    //   1197	1206	1494	finally
    //   1215	1218	1598	finally
    //   1218	1225	1598	finally
    //   1230	1307	1598	finally
    //   1467	1470	1598	finally
    //   1197	1206	1603	java/lang/Exception
  }

  // ERROR //
  public final void run()
  {
    // Byte code:
    //   0: new 153	java/lang/StringBuilder
    //   3: dup
    //   4: getstatic 119	cn/jpush/android/service/n:z	[Ljava/lang/String;
    //   7: iconst_0
    //   8: aaload
    //   9: invokespecial 246	java/lang/StringBuilder:<init>	(Ljava/lang/String;)V
    //   12: aload_0
    //   13: invokevirtual 344	cn/jpush/android/service/n:getId	()J
    //   16: invokevirtual 249	java/lang/StringBuilder:append	(J)Ljava/lang/StringBuilder;
    //   19: invokevirtual 175	java/lang/StringBuilder:toString	()Ljava/lang/String;
    //   22: pop
    //   23: invokestatic 256	cn/jpush/android/util/x:d	()V
    //   26: aload_0
    //   27: getfield 122	cn/jpush/android/service/n:b	Lcn/jpush/android/service/PushService;
    //   30: pop
    //   31: invokestatic 347	cn/jpush/android/service/PushService:c	()Z
    //   34: pop
    //   35: aload_0
    //   36: getfield 122	cn/jpush/android/service/n:b	Lcn/jpush/android/service/PushService;
    //   39: getfield 210	cn/jpush/android/service/PushService:v	I
    //   42: ifeq +23 -> 65
    //   45: invokestatic 298	cn/jpush/android/util/x:e	()V
    //   48: aload_0
    //   49: getfield 122	cn/jpush/android/service/n:b	Lcn/jpush/android/service/PushService;
    //   52: aload_0
    //   53: getfield 122	cn/jpush/android/service/n:b	Lcn/jpush/android/service/PushService;
    //   56: getfield 210	cn/jpush/android/service/PushService:v	I
    //   59: invokestatic 351	cn/jpush/android/service/PushProtocol:Close	(I)I
    //   62: putfield 210	cn/jpush/android/service/PushService:v	I
    //   65: aload_0
    //   66: getfield 122	cn/jpush/android/service/n:b	Lcn/jpush/android/service/PushService;
    //   69: invokevirtual 352	cn/jpush/android/service/PushService:d	()V
    //   72: aload_0
    //   73: getfield 122	cn/jpush/android/service/n:b	Lcn/jpush/android/service/PushService;
    //   76: invokestatic 355	cn/jpush/android/service/PushProtocol:InitConn	()I
    //   79: putfield 210	cn/jpush/android/service/PushService:v	I
    //   82: invokestatic 357	cn/jpush/android/service/PushService:h	()Ljava/lang/String;
    //   85: astore 6
    //   87: aload 6
    //   89: ifnull +57 -> 146
    //   92: invokestatic 357	cn/jpush/android/service/PushService:h	()Ljava/lang/String;
    //   95: invokestatic 363	java/net/InetAddress:getByName	(Ljava/lang/String;)Ljava/net/InetAddress;
    //   98: invokevirtual 366	java/net/InetAddress:getHostAddress	()Ljava/lang/String;
    //   101: invokestatic 369	cn/jpush/android/service/PushService:e	(Ljava/lang/String;)Ljava/lang/String;
    //   104: pop
    //   105: new 153	java/lang/StringBuilder
    //   108: dup
    //   109: getstatic 119	cn/jpush/android/service/n:z	[Ljava/lang/String;
    //   112: bipush 12
    //   114: aaload
    //   115: invokespecial 246	java/lang/StringBuilder:<init>	(Ljava/lang/String;)V
    //   118: invokestatic 371	cn/jpush/android/service/PushService:i	()Ljava/lang/String;
    //   121: invokevirtual 172	java/lang/StringBuilder:append	(Ljava/lang/String;)Ljava/lang/StringBuilder;
    //   124: getstatic 119	cn/jpush/android/service/n:z	[Ljava/lang/String;
    //   127: bipush 10
    //   129: aaload
    //   130: invokevirtual 172	java/lang/StringBuilder:append	(Ljava/lang/String;)Ljava/lang/StringBuilder;
    //   133: invokestatic 357	cn/jpush/android/service/PushService:h	()Ljava/lang/String;
    //   136: invokevirtual 172	java/lang/StringBuilder:append	(Ljava/lang/String;)Ljava/lang/StringBuilder;
    //   139: invokevirtual 175	java/lang/StringBuilder:toString	()Ljava/lang/String;
    //   142: pop
    //   143: invokestatic 188	cn/jpush/android/util/x:c	()V
    //   146: new 153	java/lang/StringBuilder
    //   149: dup
    //   150: getstatic 119	cn/jpush/android/service/n:z	[Ljava/lang/String;
    //   153: bipush 6
    //   155: aaload
    //   156: invokespecial 246	java/lang/StringBuilder:<init>	(Ljava/lang/String;)V
    //   159: invokestatic 371	cn/jpush/android/service/PushService:i	()Ljava/lang/String;
    //   162: invokevirtual 172	java/lang/StringBuilder:append	(Ljava/lang/String;)Ljava/lang/StringBuilder;
    //   165: getstatic 119	cn/jpush/android/service/n:z	[Ljava/lang/String;
    //   168: bipush 9
    //   170: aaload
    //   171: invokevirtual 172	java/lang/StringBuilder:append	(Ljava/lang/String;)Ljava/lang/StringBuilder;
    //   174: invokestatic 372	cn/jpush/android/service/PushService:j	()I
    //   177: invokevirtual 238	java/lang/StringBuilder:append	(I)Ljava/lang/StringBuilder;
    //   180: invokevirtual 175	java/lang/StringBuilder:toString	()Ljava/lang/String;
    //   183: pop
    //   184: invokestatic 188	cn/jpush/android/util/x:c	()V
    //   187: aload_0
    //   188: getfield 122	cn/jpush/android/service/n:b	Lcn/jpush/android/service/PushService;
    //   191: getfield 210	cn/jpush/android/service/PushService:v	I
    //   194: invokestatic 371	cn/jpush/android/service/PushService:i	()Ljava/lang/String;
    //   197: invokestatic 372	cn/jpush/android/service/PushService:j	()I
    //   200: invokestatic 376	cn/jpush/android/service/PushProtocol:InitPush	(ILjava/lang/String;I)I
    //   203: istore 8
    //   205: iload 8
    //   207: ifeq +77 -> 284
    //   210: new 153	java/lang/StringBuilder
    //   213: dup
    //   214: getstatic 119	cn/jpush/android/service/n:z	[Ljava/lang/String;
    //   217: bipush 7
    //   219: aaload
    //   220: invokespecial 246	java/lang/StringBuilder:<init>	(Ljava/lang/String;)V
    //   223: aload_0
    //   224: invokevirtual 344	cn/jpush/android/service/n:getId	()J
    //   227: invokevirtual 249	java/lang/StringBuilder:append	(J)Ljava/lang/StringBuilder;
    //   230: invokevirtual 175	java/lang/StringBuilder:toString	()Ljava/lang/String;
    //   233: pop
    //   234: invokestatic 188	cn/jpush/android/util/x:c	()V
    //   237: aload_0
    //   238: getfield 122	cn/jpush/android/service/n:b	Lcn/jpush/android/service/PushService;
    //   241: getfield 210	cn/jpush/android/service/PushService:v	I
    //   244: ifeq +23 -> 267
    //   247: invokestatic 298	cn/jpush/android/util/x:e	()V
    //   250: aload_0
    //   251: getfield 122	cn/jpush/android/service/n:b	Lcn/jpush/android/service/PushService;
    //   254: aload_0
    //   255: getfield 122	cn/jpush/android/service/n:b	Lcn/jpush/android/service/PushService;
    //   258: getfield 210	cn/jpush/android/service/PushService:v	I
    //   261: invokestatic 351	cn/jpush/android/service/PushProtocol:Close	(I)I
    //   264: putfield 210	cn/jpush/android/service/PushService:v	I
    //   267: aload_0
    //   268: getfield 122	cn/jpush/android/service/n:b	Lcn/jpush/android/service/PushService;
    //   271: iconst_0
    //   272: invokevirtual 378	cn/jpush/android/service/PushService:f	(I)V
    //   275: return
    //   276: astore 4
    //   278: invokestatic 188	cn/jpush/android/util/x:c	()V
    //   281: goto -216 -> 65
    //   284: getstatic 119	cn/jpush/android/service/n:z	[Ljava/lang/String;
    //   287: iconst_3
    //   288: aaload
    //   289: astore 10
    //   291: iconst_1
    //   292: anewarray 158	java/lang/Object
    //   295: astore 11
    //   297: aload 11
    //   299: iconst_0
    //   300: iload 8
    //   302: invokestatic 333	java/lang/Integer:valueOf	(I)Ljava/lang/Integer;
    //   305: aastore
    //   306: aload 10
    //   308: aload 11
    //   310: invokestatic 168	java/lang/String:format	(Ljava/lang/String;[Ljava/lang/Object;)Ljava/lang/String;
    //   313: pop
    //   314: invokestatic 188	cn/jpush/android/util/x:c	()V
    //   317: invokestatic 380	cn/jpush/android/service/PushService:k	()Z
    //   320: ifne +17 -> 337
    //   323: aload_0
    //   324: getfield 122	cn/jpush/android/service/n:b	Lcn/jpush/android/service/PushService;
    //   327: invokevirtual 214	cn/jpush/android/service/PushService:getApplicationContext	()Landroid/content/Context;
    //   330: invokestatic 383	cn/jpush/android/service/PushService:c	(Landroid/content/Context;)Z
    //   333: invokestatic 386	cn/jpush/android/service/PushService:e	(Z)Z
    //   336: pop
    //   337: invokestatic 380	cn/jpush/android/service/PushService:k	()Z
    //   340: ifeq +17 -> 357
    //   343: getstatic 179	cn/jpush/android/service/PushService:s	J
    //   346: lconst_0
    //   347: lcmp
    //   348: ifeq +9 -> 357
    //   351: getstatic 143	cn/jpush/android/service/PushService:t	Ljava/lang/String;
    //   354: ifnonnull +10 -> 364
    //   357: aload_0
    //   358: getfield 122	cn/jpush/android/service/n:b	Lcn/jpush/android/service/PushService;
    //   361: invokevirtual 387	cn/jpush/android/service/PushService:e	()V
    //   364: getstatic 179	cn/jpush/android/service/PushService:s	J
    //   367: lconst_0
    //   368: lcmp
    //   369: ifeq +380 -> 749
    //   372: aload_0
    //   373: invokespecial 389	cn/jpush/android/service/n:a	()I
    //   376: istore 8
    //   378: iload 8
    //   380: ifeq +11 -> 391
    //   383: iload 8
    //   385: sipush 9999
    //   388: if_icmpne +292 -> 680
    //   391: getstatic 119	cn/jpush/android/service/n:z	[Ljava/lang/String;
    //   394: iconst_2
    //   395: aaload
    //   396: new 153	java/lang/StringBuilder
    //   399: dup
    //   400: getstatic 119	cn/jpush/android/service/n:z	[Ljava/lang/String;
    //   403: iconst_5
    //   404: aaload
    //   405: invokespecial 246	java/lang/StringBuilder:<init>	(Ljava/lang/String;)V
    //   408: aload_0
    //   409: getfield 122	cn/jpush/android/service/n:b	Lcn/jpush/android/service/PushService;
    //   412: invokevirtual 214	cn/jpush/android/service/PushService:getApplicationContext	()Landroid/content/Context;
    //   415: invokestatic 392	cn/jpush/android/util/a:u	(Landroid/content/Context;)Ljava/lang/String;
    //   418: invokevirtual 172	java/lang/StringBuilder:append	(Ljava/lang/String;)Ljava/lang/StringBuilder;
    //   421: invokevirtual 175	java/lang/StringBuilder:toString	()Ljava/lang/String;
    //   424: invokestatic 394	cn/jpush/android/util/x:b	(Ljava/lang/String;Ljava/lang/String;)V
    //   427: aload_0
    //   428: getfield 122	cn/jpush/android/service/n:b	Lcn/jpush/android/service/PushService;
    //   431: iconst_0
    //   432: invokestatic 397	cn/jpush/android/service/PushService:a	(Lcn/jpush/android/service/PushService;I)I
    //   435: pop
    //   436: invokestatic 400	cn/jpush/android/service/PushService:l	()Z
    //   439: ifeq +10 -> 449
    //   442: aload_0
    //   443: getfield 122	cn/jpush/android/service/n:b	Lcn/jpush/android/service/PushService;
    //   446: invokestatic 402	cn/jpush/android/service/PushService:a	(Lcn/jpush/android/service/PushService;)V
    //   449: aload_0
    //   450: getfield 122	cn/jpush/android/service/n:b	Lcn/jpush/android/service/PushService;
    //   453: invokevirtual 404	cn/jpush/android/service/PushService:g	()V
    //   456: iload 8
    //   458: sipush 9999
    //   461: if_icmpne +13 -> 474
    //   464: aload_0
    //   465: getfield 122	cn/jpush/android/service/n:b	Lcn/jpush/android/service/PushService;
    //   468: sipush 6000
    //   471: invokestatic 407	cn/jpush/android/service/PushService:b	(Lcn/jpush/android/service/PushService;I)V
    //   474: aload_0
    //   475: getfield 122	cn/jpush/android/service/n:b	Lcn/jpush/android/service/PushService;
    //   478: iconst_1
    //   479: getstatic 119	cn/jpush/android/service/n:z	[Ljava/lang/String;
    //   482: bipush 8
    //   484: aaload
    //   485: invokevirtual 410	cn/jpush/android/service/PushService:a	(ILjava/lang/String;)V
    //   488: aload_0
    //   489: getfield 126	cn/jpush/android/service/n:c	Z
    //   492: ifne +99 -> 591
    //   495: aload_0
    //   496: getfield 122	cn/jpush/android/service/n:b	Lcn/jpush/android/service/PushService;
    //   499: getfield 210	cn/jpush/android/service/PushService:v	I
    //   502: aload_0
    //   503: getfield 122	cn/jpush/android/service/n:b	Lcn/jpush/android/service/PushService;
    //   506: getfield 413	cn/jpush/android/service/PushService:w	[B
    //   509: ldc_w 414
    //   512: invokestatic 418	cn/jpush/android/service/PushProtocol:RecvPush	(I[BI)I
    //   515: istore 8
    //   517: getstatic 119	cn/jpush/android/service/n:z	[Ljava/lang/String;
    //   520: iconst_1
    //   521: aaload
    //   522: astore 16
    //   524: iconst_1
    //   525: anewarray 158	java/lang/Object
    //   528: astore 17
    //   530: aload 17
    //   532: iconst_0
    //   533: iload 8
    //   535: invokestatic 333	java/lang/Integer:valueOf	(I)Ljava/lang/Integer;
    //   538: aastore
    //   539: aload 16
    //   541: aload 17
    //   543: invokestatic 168	java/lang/String:format	(Ljava/lang/String;[Ljava/lang/Object;)Ljava/lang/String;
    //   546: pop
    //   547: invokestatic 188	cn/jpush/android/util/x:c	()V
    //   550: iload 8
    //   552: ifle +117 -> 669
    //   555: invokestatic 400	cn/jpush/android/service/PushService:l	()Z
    //   558: ifeq +10 -> 568
    //   561: aload_0
    //   562: getfield 122	cn/jpush/android/service/n:b	Lcn/jpush/android/service/PushService;
    //   565: invokestatic 402	cn/jpush/android/service/PushService:a	(Lcn/jpush/android/service/PushService;)V
    //   568: aload_0
    //   569: getfield 122	cn/jpush/android/service/n:b	Lcn/jpush/android/service/PushService;
    //   572: iload 8
    //   574: invokevirtual 420	cn/jpush/android/service/PushService:e	(I)V
    //   577: ldc2_w 421
    //   580: invokestatic 426	java/lang/Thread:sleep	(J)V
    //   583: goto -95 -> 488
    //   586: astore 19
    //   588: invokestatic 428	cn/jpush/android/util/x:h	()V
    //   591: aload_0
    //   592: iconst_0
    //   593: putfield 128	cn/jpush/android/service/n:a	Z
    //   596: new 153	java/lang/StringBuilder
    //   599: dup
    //   600: getstatic 119	cn/jpush/android/service/n:z	[Ljava/lang/String;
    //   603: bipush 13
    //   605: aaload
    //   606: invokespecial 246	java/lang/StringBuilder:<init>	(Ljava/lang/String;)V
    //   609: aload_0
    //   610: invokevirtual 344	cn/jpush/android/service/n:getId	()J
    //   613: invokevirtual 249	java/lang/StringBuilder:append	(J)Ljava/lang/StringBuilder;
    //   616: invokevirtual 175	java/lang/StringBuilder:toString	()Ljava/lang/String;
    //   619: pop
    //   620: invokestatic 429	cn/jpush/android/util/x:b	()V
    //   623: aload_0
    //   624: getfield 122	cn/jpush/android/service/n:b	Lcn/jpush/android/service/PushService;
    //   627: getfield 210	cn/jpush/android/service/PushService:v	I
    //   630: ifeq +23 -> 653
    //   633: invokestatic 298	cn/jpush/android/util/x:e	()V
    //   636: aload_0
    //   637: getfield 122	cn/jpush/android/service/n:b	Lcn/jpush/android/service/PushService;
    //   640: aload_0
    //   641: getfield 122	cn/jpush/android/service/n:b	Lcn/jpush/android/service/PushService;
    //   644: getfield 210	cn/jpush/android/service/PushService:v	I
    //   647: invokestatic 351	cn/jpush/android/service/PushProtocol:Close	(I)I
    //   650: putfield 210	cn/jpush/android/service/PushService:v	I
    //   653: aload_0
    //   654: getfield 122	cn/jpush/android/service/n:b	Lcn/jpush/android/service/PushService;
    //   657: iload 8
    //   659: invokevirtual 378	cn/jpush/android/service/PushService:f	(I)V
    //   662: return
    //   663: astore 5
    //   665: invokestatic 428	cn/jpush/android/util/x:h	()V
    //   668: return
    //   669: iload 8
    //   671: sipush -994
    //   674: if_icmpne -83 -> 591
    //   677: goto -100 -> 577
    //   680: getstatic 119	cn/jpush/android/service/n:z	[Ljava/lang/String;
    //   683: iconst_2
    //   684: aaload
    //   685: new 153	java/lang/StringBuilder
    //   688: dup
    //   689: getstatic 119	cn/jpush/android/service/n:z	[Ljava/lang/String;
    //   692: bipush 11
    //   694: aaload
    //   695: invokespecial 246	java/lang/StringBuilder:<init>	(Ljava/lang/String;)V
    //   698: aload_0
    //   699: getfield 122	cn/jpush/android/service/n:b	Lcn/jpush/android/service/PushService;
    //   702: getfield 210	cn/jpush/android/service/PushService:v	I
    //   705: invokestatic 433	cn/jpush/android/service/PushProtocol:GetEsg	(I)Ljava/lang/String;
    //   708: invokevirtual 172	java/lang/StringBuilder:append	(Ljava/lang/String;)Ljava/lang/StringBuilder;
    //   711: invokevirtual 175	java/lang/StringBuilder:toString	()Ljava/lang/String;
    //   714: invokestatic 394	cn/jpush/android/util/x:b	(Ljava/lang/String;Ljava/lang/String;)V
    //   717: iload 8
    //   719: ifle +13 -> 732
    //   722: aload_0
    //   723: getfield 122	cn/jpush/android/service/n:b	Lcn/jpush/android/service/PushService;
    //   726: invokevirtual 435	cn/jpush/android/service/PushService:f	()V
    //   729: goto -106 -> 623
    //   732: iload 8
    //   734: ifge -111 -> 623
    //   737: aload_0
    //   738: getfield 122	cn/jpush/android/service/n:b	Lcn/jpush/android/service/PushService;
    //   741: lconst_0
    //   742: invokestatic 438	cn/jpush/android/service/PushService:a	(Lcn/jpush/android/service/PushService;J)J
    //   745: pop2
    //   746: goto -123 -> 623
    //   749: getstatic 119	cn/jpush/android/service/n:z	[Ljava/lang/String;
    //   752: iconst_2
    //   753: aaload
    //   754: new 153	java/lang/StringBuilder
    //   757: dup
    //   758: getstatic 119	cn/jpush/android/service/n:z	[Ljava/lang/String;
    //   761: iconst_4
    //   762: aaload
    //   763: invokespecial 246	java/lang/StringBuilder:<init>	(Ljava/lang/String;)V
    //   766: aload_0
    //   767: invokevirtual 344	cn/jpush/android/service/n:getId	()J
    //   770: invokevirtual 249	java/lang/StringBuilder:append	(J)Ljava/lang/StringBuilder;
    //   773: invokevirtual 175	java/lang/StringBuilder:toString	()Ljava/lang/String;
    //   776: invokestatic 394	cn/jpush/android/util/x:b	(Ljava/lang/String;Ljava/lang/String;)V
    //   779: goto -156 -> 623
    //   782: astore 14
    //   784: goto -328 -> 456
    //   787: astore 23
    //   789: goto -643 -> 146
    //
    // Exception table:
    //   from	to	target	type
    //   35	65	276	java/lang/Exception
    //   577	583	586	java/lang/InterruptedException
    //   65	87	663	java/lang/Exception
    //   92	146	663	java/lang/Exception
    //   146	205	663	java/lang/Exception
    //   210	267	663	java/lang/Exception
    //   267	275	663	java/lang/Exception
    //   284	337	663	java/lang/Exception
    //   337	357	663	java/lang/Exception
    //   357	364	663	java/lang/Exception
    //   364	378	663	java/lang/Exception
    //   391	449	663	java/lang/Exception
    //   464	474	663	java/lang/Exception
    //   474	488	663	java/lang/Exception
    //   488	550	663	java/lang/Exception
    //   555	568	663	java/lang/Exception
    //   568	577	663	java/lang/Exception
    //   577	583	663	java/lang/Exception
    //   588	591	663	java/lang/Exception
    //   591	623	663	java/lang/Exception
    //   623	653	663	java/lang/Exception
    //   653	662	663	java/lang/Exception
    //   680	717	663	java/lang/Exception
    //   722	729	663	java/lang/Exception
    //   737	746	663	java/lang/Exception
    //   749	779	663	java/lang/Exception
    //   449	456	782	java/lang/Exception
    //   92	146	787	java/net/UnknownHostException
  }
}

/* Location:           /Users/mattshapiro/Downloads/dex2jar/com.dji.smartphone.downloader-dex2jar.jar
 * Qualified Name:     cn.jpush.android.service.n
 * JD-Core Version:    0.6.2
 */