package cn.jpush.android.util;

final class o
  implements Runnable
{
  o(String paramString1, String paramString2, p paramp)
  {
  }

  // ERROR //
  public final void run()
  {
    // Byte code:
    //   0: invokestatic 32	cn/jpush/android/util/n:a	()Lorg/apache/http/impl/client/DefaultHttpClient;
    //   3: astore_1
    //   4: new 34	org/apache/http/client/methods/HttpGet
    //   7: dup
    //   8: aload_0
    //   9: getfield 15	cn/jpush/android/util/o:a	Ljava/lang/String;
    //   12: invokespecial 37	org/apache/http/client/methods/HttpGet:<init>	(Ljava/lang/String;)V
    //   15: astore_2
    //   16: aload_1
    //   17: aload_2
    //   18: invokevirtual 43	org/apache/http/impl/client/DefaultHttpClient:execute	(Lorg/apache/http/client/methods/HttpUriRequest;)Lorg/apache/http/HttpResponse;
    //   21: astore 19
    //   23: aload 19
    //   25: invokeinterface 49 1 0
    //   30: invokeinterface 55 1 0
    //   35: sipush 200
    //   38: if_icmpne +352 -> 390
    //   41: aload 19
    //   43: invokeinterface 59 1 0
    //   48: invokeinterface 65 1 0
    //   53: lstore 20
    //   55: aload_0
    //   56: getfield 15	cn/jpush/android/util/o:a	Ljava/lang/String;
    //   59: ldc 67
    //   61: invokevirtual 73	java/lang/String:lastIndexOf	(Ljava/lang/String;)I
    //   64: istore 22
    //   66: aload_0
    //   67: getfield 15	cn/jpush/android/util/o:a	Ljava/lang/String;
    //   70: iload 22
    //   72: iconst_1
    //   73: iadd
    //   74: invokevirtual 77	java/lang/String:substring	(I)Ljava/lang/String;
    //   77: astore 23
    //   79: new 79	java/io/File
    //   82: dup
    //   83: aload_0
    //   84: getfield 17	cn/jpush/android/util/o:b	Ljava/lang/String;
    //   87: aload 23
    //   89: invokespecial 82	java/io/File:<init>	(Ljava/lang/String;Ljava/lang/String;)V
    //   92: astore 24
    //   94: aload 24
    //   96: invokevirtual 86	java/io/File:exists	()Z
    //   99: ifeq +187 -> 286
    //   102: aload 24
    //   104: invokevirtual 89	java/io/File:length	()J
    //   107: lload 20
    //   109: lcmp
    //   110: ifne +26 -> 136
    //   113: lload 20
    //   115: lconst_0
    //   116: lcmp
    //   117: ifeq +19 -> 136
    //   120: aload_0
    //   121: getfield 19	cn/jpush/android/util/o:c	Lcn/jpush/android/util/p;
    //   124: iconst_1
    //   125: aload 24
    //   127: invokevirtual 93	java/io/File:getAbsolutePath	()Ljava/lang/String;
    //   130: invokeinterface 98 3 0
    //   135: return
    //   136: aload 24
    //   138: invokevirtual 101	java/io/File:delete	()Z
    //   141: pop
    //   142: aload 24
    //   144: invokevirtual 104	java/io/File:createNewFile	()Z
    //   147: pop
    //   148: aload 19
    //   150: invokeinterface 59 1 0
    //   155: invokeinterface 108 1 0
    //   160: astore 27
    //   162: aload 27
    //   164: astore 5
    //   166: new 110	java/io/BufferedInputStream
    //   169: dup
    //   170: aload 5
    //   172: invokespecial 113	java/io/BufferedInputStream:<init>	(Ljava/io/InputStream;)V
    //   175: astore 4
    //   177: new 115	java/io/FileOutputStream
    //   180: dup
    //   181: aload 24
    //   183: invokespecial 118	java/io/FileOutputStream:<init>	(Ljava/io/File;)V
    //   186: astore 6
    //   188: sipush 1024
    //   191: newarray byte
    //   193: astore 29
    //   195: aload 4
    //   197: aload 29
    //   199: invokevirtual 122	java/io/BufferedInputStream:read	([B)I
    //   202: istore 30
    //   204: iload 30
    //   206: iconst_m1
    //   207: if_icmpeq +129 -> 336
    //   210: aload 6
    //   212: aload 29
    //   214: iconst_0
    //   215: iload 30
    //   217: invokevirtual 126	java/io/FileOutputStream:write	([BII)V
    //   220: goto -25 -> 195
    //   223: astore 28
    //   225: aload 6
    //   227: astore 12
    //   229: aload 4
    //   231: astore 13
    //   233: aload 5
    //   235: astore 14
    //   237: invokestatic 131	cn/jpush/android/util/x:h	()V
    //   240: aload_0
    //   241: getfield 19	cn/jpush/android/util/o:c	Lcn/jpush/android/util/p;
    //   244: iconst_0
    //   245: ldc 133
    //   247: invokeinterface 98 3 0
    //   252: aload 12
    //   254: ifnull +8 -> 262
    //   257: aload 12
    //   259: invokevirtual 136	java/io/FileOutputStream:close	()V
    //   262: aload 13
    //   264: ifnull +8 -> 272
    //   267: aload 13
    //   269: invokevirtual 137	java/io/BufferedInputStream:close	()V
    //   272: aload 14
    //   274: ifnull +294 -> 568
    //   277: aload 14
    //   279: invokevirtual 140	java/io/InputStream:close	()V
    //   282: return
    //   283: astore 16
    //   285: return
    //   286: new 79	java/io/File
    //   289: dup
    //   290: aload_0
    //   291: getfield 17	cn/jpush/android/util/o:b	Ljava/lang/String;
    //   294: invokespecial 141	java/io/File:<init>	(Ljava/lang/String;)V
    //   297: astore 25
    //   299: aload 25
    //   301: invokevirtual 86	java/io/File:exists	()Z
    //   304: ifne +9 -> 313
    //   307: aload 25
    //   309: invokevirtual 144	java/io/File:mkdirs	()Z
    //   312: pop
    //   313: aload 24
    //   315: invokevirtual 104	java/io/File:createNewFile	()Z
    //   318: pop
    //   319: goto -171 -> 148
    //   322: astore 11
    //   324: aconst_null
    //   325: astore 12
    //   327: aconst_null
    //   328: astore 13
    //   330: aconst_null
    //   331: astore 14
    //   333: goto -96 -> 237
    //   336: aload 6
    //   338: invokevirtual 147	java/io/FileOutputStream:flush	()V
    //   341: aload_0
    //   342: getfield 19	cn/jpush/android/util/o:c	Lcn/jpush/android/util/p;
    //   345: iconst_1
    //   346: aload 24
    //   348: invokevirtual 93	java/io/File:getAbsolutePath	()Ljava/lang/String;
    //   351: invokeinterface 98 3 0
    //   356: aload 6
    //   358: ifnull +8 -> 366
    //   361: aload 6
    //   363: invokevirtual 136	java/io/FileOutputStream:close	()V
    //   366: aload 4
    //   368: ifnull +8 -> 376
    //   371: aload 4
    //   373: invokevirtual 137	java/io/BufferedInputStream:close	()V
    //   376: aload 5
    //   378: ifnull +190 -> 568
    //   381: aload 5
    //   383: invokevirtual 140	java/io/InputStream:close	()V
    //   386: return
    //   387: astore 31
    //   389: return
    //   390: aload_0
    //   391: getfield 19	cn/jpush/android/util/o:c	Lcn/jpush/android/util/p;
    //   394: iconst_0
    //   395: ldc 133
    //   397: invokeinterface 98 3 0
    //   402: return
    //   403: astore_3
    //   404: aconst_null
    //   405: astore 4
    //   407: aconst_null
    //   408: astore 5
    //   410: aconst_null
    //   411: astore 6
    //   413: aload_3
    //   414: astore 7
    //   416: aload 6
    //   418: ifnull +8 -> 426
    //   421: aload 6
    //   423: invokevirtual 136	java/io/FileOutputStream:close	()V
    //   426: aload 4
    //   428: ifnull +8 -> 436
    //   431: aload 4
    //   433: invokevirtual 137	java/io/BufferedInputStream:close	()V
    //   436: aload 5
    //   438: ifnull +8 -> 446
    //   441: aload 5
    //   443: invokevirtual 140	java/io/InputStream:close	()V
    //   446: aload 7
    //   448: athrow
    //   449: astore 33
    //   451: goto -85 -> 366
    //   454: astore 32
    //   456: goto -80 -> 376
    //   459: astore 18
    //   461: goto -199 -> 262
    //   464: astore 17
    //   466: goto -194 -> 272
    //   469: astore 10
    //   471: goto -45 -> 426
    //   474: astore 9
    //   476: goto -40 -> 436
    //   479: astore 8
    //   481: goto -35 -> 446
    //   484: astore 37
    //   486: aload 37
    //   488: astore 7
    //   490: aconst_null
    //   491: astore 6
    //   493: aconst_null
    //   494: astore 4
    //   496: goto -80 -> 416
    //   499: astore 35
    //   501: aload 35
    //   503: astore 7
    //   505: aconst_null
    //   506: astore 6
    //   508: goto -92 -> 416
    //   511: astore 7
    //   513: goto -97 -> 416
    //   516: astore 15
    //   518: aload 14
    //   520: astore 5
    //   522: aload 13
    //   524: astore 4
    //   526: aload 12
    //   528: astore 6
    //   530: aload 15
    //   532: astore 7
    //   534: goto -118 -> 416
    //   537: astore 36
    //   539: aload 5
    //   541: astore 14
    //   543: aconst_null
    //   544: astore 12
    //   546: aconst_null
    //   547: astore 13
    //   549: goto -312 -> 237
    //   552: astore 34
    //   554: aload 4
    //   556: astore 13
    //   558: aload 5
    //   560: astore 14
    //   562: aconst_null
    //   563: astore 12
    //   565: goto -328 -> 237
    //   568: return
    //
    // Exception table:
    //   from	to	target	type
    //   188	195	223	java/lang/Exception
    //   195	204	223	java/lang/Exception
    //   210	220	223	java/lang/Exception
    //   336	356	223	java/lang/Exception
    //   277	282	283	java/io/IOException
    //   16	113	322	java/lang/Exception
    //   120	135	322	java/lang/Exception
    //   136	148	322	java/lang/Exception
    //   148	162	322	java/lang/Exception
    //   286	313	322	java/lang/Exception
    //   313	319	322	java/lang/Exception
    //   390	402	322	java/lang/Exception
    //   381	386	387	java/io/IOException
    //   16	113	403	finally
    //   120	135	403	finally
    //   136	148	403	finally
    //   148	162	403	finally
    //   286	313	403	finally
    //   313	319	403	finally
    //   390	402	403	finally
    //   361	366	449	java/io/IOException
    //   371	376	454	java/io/IOException
    //   257	262	459	java/io/IOException
    //   267	272	464	java/io/IOException
    //   421	426	469	java/io/IOException
    //   431	436	474	java/io/IOException
    //   441	446	479	java/io/IOException
    //   166	177	484	finally
    //   177	188	499	finally
    //   188	195	511	finally
    //   195	204	511	finally
    //   210	220	511	finally
    //   336	356	511	finally
    //   237	252	516	finally
    //   166	177	537	java/lang/Exception
    //   177	188	552	java/lang/Exception
  }
}

/* Location:           /Users/mattshapiro/Downloads/dex2jar/com.dji.smartphone.downloader-dex2jar.jar
 * Qualified Name:     cn.jpush.android.util.o
 * JD-Core Version:    0.6.2
 */